{"rf-o5153-701470-1-750860":{"aff":["repetition"],"id":"rf-o5153-701470-1-750860","loc":[{"line":"o5153-l37420","words":"o5153-701470 o5153-701540 o5153-701560"}],"mech":"comp","name":"assonance","patt":"/ɑː/","phon":"ph12","resp":"#AH"},"rf-o5153-701490-1-741817":{"aff":["repetition","position"],"id":"rf-o5153-701490-1-741817","loc":[{"line":"o5153-l37420","words":"o5153-701490 o5153-701510 o5153-701560"}],"mech":"comp","name":"alliteration","patt":"/h/","phon":"ph42","resp":"#AH"},"rf-o5153-701490-1-750861":{"aff":["repetition"],"id":"rf-o5153-701490-1-750861","loc":[{"line":"o5153-l37420","words":"o5153-701490 o5153-701550"}],"mech":"comp","name":"assonance","patt":"/uː/","phon":"ph09","resp":"#AH"},"rf-o5153-701510-1-765544":{"aff":["repetition"],"id":"rf-o5153-701510-1-765544","loc":[{"line":"o5153-l37420","words":"o5153-701510 o5153-701540"}],"mech":"comp","name":"consonance","patt":"/s/","phon":"ph38","resp":"#AH"},"rf-o5153-701520-1-770033":{"aff":["omission","reduction"],"id":"rf-o5153-701520-1-770033","loc":[{"line":"o5153-l37420","words":"o5153-701520"}],"mech":"comp","name":"syncope","patt":"judg'd","resp":"#AH"},"rf-o5153-701540-1-765545":{"aff":["repetition"],"id":"rf-o5153-701540-1-765545","loc":[{"line":"o5153-l37420","words":"o5153-701540 o5153-701550"}],"mech":"comp","name":"consonance","patt":"/t/","phon":"ph28","resp":"#AH"},"rf-o5153-701600-1-765546":{"aff":["repetition"],"id":"rf-o5153-701600-1-765546","loc":[{"line":"o5153-l37425","words":"o5153-701600 o5153-701620 o5153-701640"}],"mech":"comp","name":"consonance","patt":"/t/","phon":"ph28","resp":"#AH"},"rf-o5153-701670-1-741818":{"aff":["repetition","position"],"id":"rf-o5153-701670-1-741818","loc":[{"line":"o5153-l37430","words":"o5153-701670 o5153-701690"}],"mech":"comp","name":"alliteration","patt":"/f/","phon":"ph34","resp":"#AH"},"rf-o5153-701670-1-765548":{"aff":["repetition"],"id":"rf-o5153-701670-1-765548","loc":[{"line":"o5153-l37430","words":"o5153-701670 o5153-701690"}],"mech":"comp","name":"consonance","patt":"/l/","phon":"ph44","resp":"#AH"},"rf-o5153-701680-1-750862":{"aff":["repetition"],"id":"rf-o5153-701680-1-750862","loc":[{"line":"o5153-l37430","words":"o5153-701680 o5153-701690"}],"mech":"comp","name":"assonance","patt":"/ɔː/","phon":"ph11","resp":"#AH"},"rf-o5153-701680-1-765549":{"aff":["repetition"],"id":"rf-o5153-701680-1-765549","loc":[{"line":"o5153-l37430","words":"o5153-701680 o5153-701710"}],"mech":"comp","name":"consonance","patt":"/r/","phon":"ph45","resp":"#AH"},"rf-o5153-701740-1-750863":{"aff":["repetition"],"id":"rf-o5153-701740-1-750863","loc":[{"line":"o5153-l37435","words":"o5153-701740 o5153-701770"}],"mech":"comp","name":"assonance","patt":"/ɜː/","phon":"ph10","resp":"#AH"},"rf-o5153-701740-1-765550":{"aff":["repetition"],"id":"rf-o5153-701740-1-765550","loc":[{"line":"o5153-l37435","words":"o5153-701740 o5153-701770"}],"mech":"comp","name":"consonance","patt":"/s/","phon":"ph38","resp":"#AH"},"rf-o5153-701740-1-765551":{"aff":["repetition"],"id":"rf-o5153-701740-1-765551","loc":[{"line":"o5153-l37435","words":"o5153-701740 o5153-701750 o5153-701770"}],"mech":"comp","name":"consonance","patt":"/t/","phon":"ph28","resp":"#AH"},"rf-o5153-701840-1-750864":{"aff":["repetition"],"id":"rf-o5153-701840-1-750864","loc":[{"line":"o5153-l37440","words":"o5153-701840 o5153-701890"}],"mech":"comp","name":"assonance","patt":"/ɪ/","phon":"ph01","resp":"#AH"},"rf-o5153-701870-1-765552":{"aff":["repetition"],"id":"rf-o5153-701870-1-765552","loc":[{"line":"o5153-l37440","words":"o5153-701870 o5153-701890"}],"mech":"comp","name":"consonance","patt":"/d/","phon":"ph29","resp":"#AH"},"rf-o5153-701920-1-741819":{"aff":["repetition","position"],"id":"rf-o5153-701920-1-741819","loc":[{"line":"o5153-l37445","words":"o5153-701920 o5153-701930"}],"mech":"comp","name":"alliteration","patt":"/s/","phon":"ph38","resp":"#AH"},"rf-o5153-701920-1-765554":{"aff":["repetition"],"id":"rf-o5153-701920-1-765554","loc":[{"line":"o5153-l37445","words":"o5153-701920 o5153-701980"}],"mech":"comp","name":"consonance","patt":"/v/","phon":"ph35","resp":"#AH"},"rf-o5153-701930-1-750865":{"aff":["repetition"],"id":"rf-o5153-701930-1-750865","loc":[{"line":"o5153-l37445","words":"o5153-701930 o5153-701970 o5153-701980"}],"mech":"comp","name":"assonance","patt":"/ɪ/","phon":"ph01","resp":"#AH"},"rf-o5153-701930-1-765555":{"aff":["repetition"],"id":"rf-o5153-701930-1-765555","loc":[{"line":"o5153-l37445","words":"o5153-701930 o5153-701980"}],"mech":"comp","name":"consonance","patt":"/l/","phon":"ph44","resp":"#AH"},"rf-o5153-701960-1-770034":{"aff":["omission","reduction"],"id":"rf-o5153-701960-1-770034","loc":[{"line":"o5153-l37445","words":"o5153-701960"}],"mech":"comp","name":"syncope","patt":"deck'd","resp":"#AH"},"rf-o5153-702010-1-750866":{"aff":["repetition"],"id":"rf-o5153-702010-1-750866","loc":[{"line":"o5153-l37450","words":"o5153-702010 o5153-702030"}],"mech":"comp","name":"assonance","patt":"/aɪ/","phon":"ph14","resp":"#AH"},"rf-o5153-702010-1-750867":{"aff":["repetition"],"id":"rf-o5153-702010-1-750867","loc":[{"line":"o5153-l37450","words":"o5153-702010 o5153-702020 o5153-702050 o5153-702070"}],"mech":"comp","name":"assonance","patt":"/ɪ/","phon":"ph01","resp":"#AH"},"rf-o5153-702010-1-765556":{"aff":["repetition"],"id":"rf-o5153-702010-1-765556","loc":[{"line":"o5153-l37450","words":"o5153-702010 o5153-702050"}],"mech":"comp","name":"consonance","patt":"/g/","phon":"ph31","resp":"#AH"},"rf-o5153-702010-1-770035":{"aff":["omission","reduction"],"id":"rf-o5153-702010-1-770035","loc":[{"line":"o5153-l37450","words":"o5153-702010"}],"mech":"comp","name":"syncope","patt":"Disguis'd","resp":"#AH"},"rf-o5153-702020-1-765557":{"aff":["repetition"],"id":"rf-o5153-702020-1-765557","loc":[{"line":"o5153-l37450","words":"o5153-702020 o5153-702070"}],"mech":"comp","name":"consonance","patt":"/ð/","phon":"ph37","resp":"#AH"},"rf-o5153-702020-1-765558":{"aff":["repetition"],"id":"rf-o5153-702020-1-765558","loc":[{"line":"o5153-l37450","words":"o5153-702020 o5153-702070"}],"mech":"comp","name":"consonance","patt":"/w/","phon":"ph46","resp":"#AH"},"rf-o5153-702020-1-766754":{"aff":["repetition"],"id":"rf-o5153-702020-1-766754","loc":[{"line":"o5153-l37450","words":"o5153-702020 o5153-702070"}],"mech":"comp","name":"diacope","patt":"with/with","resp":"#AH"},"rf-o5153-702060-1-770036":{"aff":["omission","reduction"],"id":"rf-o5153-702060-1-770036","loc":[{"line":"o5153-l37450","words":"o5153-702060"}],"mech":"comp","name":"syncope","patt":"o'er","resp":"#AH"},"rf-o5153-702130-1-750868":{"aff":["repetition"],"id":"rf-o5153-702130-1-750868","loc":[{"line":"o5153-l37455","words":"o5153-702130 o5153-702150 o5153-702160"}],"mech":"comp","name":"assonance","patt":"/ɪ/","phon":"ph01","resp":"#AH"},"rf-o5153-702130-1-765559":{"aff":["repetition"],"id":"rf-o5153-702130-1-765559","loc":[{"line":"o5153-l37455","words":"o5153-702130 o5153-702150"}],"mech":"comp","name":"consonance","patt":"/l/","phon":"ph44","resp":"#AH"},"rf-o5153-702160-1-770037":{"aff":["omission","reduction"],"id":"rf-o5153-702160-1-770037","loc":[{"line":"o5153-l37455","words":"o5153-702160"}],"mech":"comp","name":"syncope","patt":"preferr'd","resp":"#AH"},"rf-o5153-702200-1-741820":{"aff":["repetition","position"],"id":"rf-o5153-702200-1-741820","loc":[{"line":"o5153-l37460","words":"o5153-702200 o5153-702230"}],"mech":"comp","name":"alliteration","patt":"/b/","phon":"ph27","resp":"#AH"},"rf-o5153-702200-1-765560":{"aff":["repetition"],"id":"rf-o5153-702200-1-765560","loc":[{"line":"o5153-l37460","words":"o5153-702200 o5153-702260"}],"mech":"comp","name":"consonance","patt":"/n/","phon":"ph24","resp":"#AH"},"rf-o5153-702210-1-750869":{"aff":["repetition"],"id":"rf-o5153-702210-1-750869","loc":[{"line":"o5153-l37460","words":"o5153-702210 o5153-702230"}],"mech":"comp","name":"assonance","patt":"/aɪ/","phon":"ph14","resp":"#AH"},"rf-o5153-702280-1-750870":{"aff":["repetition"],"id":"rf-o5153-702280-1-750870","loc":[{"line":"o5153-l37465","words":"o5153-702280 o5153-702320"}],"mech":"comp","name":"assonance","patt":"/ɔː/","phon":"ph11","resp":"#AH"},"rf-o5153-702350-1-765562":{"aff":["repetition"],"id":"rf-o5153-702350-1-765562","loc":[{"line":"o5153-l37470","words":"o5153-702350 o5153-702390"}],"mech":"comp","name":"consonance","patt":"/z/","phon":"ph39","resp":"#AH"},"rf-o5153-702360-1-765563":{"aff":["repetition"],"id":"rf-o5153-702360-1-765563","loc":[{"line":"o5153-l37470","words":"o5153-702360 o5153-702400 o5153-702410"}],"mech":"comp","name":"consonance","patt":"/s/","phon":"ph38","resp":"#AH"},"rf-o5153-702360-1-770038":{"aff":["omission","reduction"],"id":"rf-o5153-702360-1-770038","loc":[{"line":"o5153-l37470","words":"o5153-702360"}],"mech":"comp","name":"syncope","patt":"thou'st","resp":"#AH"},"rf-o5153-702390-1-741821":{"aff":["repetition","position"],"id":"rf-o5153-702390-1-741821","loc":[{"line":"o5153-l37470","words":"o5153-702390 o5153-702400"}],"mech":"comp","name":"alliteration","patt":"/b/","phon":"ph27","resp":"#AH"},"rf-o5153-702440-1-750871":{"aff":["repetition"],"id":"rf-o5153-702440-1-750871","loc":[{"line":"o5153-l37475","words":"o5153-702440 o5153-702450 o5153-702470"}],"mech":"comp","name":"assonance","patt":"/e/","phon":"ph03","resp":"#AH"},"rf-o5153-702450-1-741822":{"aff":["repetition","position"],"id":"rf-o5153-702450-1-741822","loc":[{"line":"o5153-l37475","words":"o5153-702450 o5153-702470"}],"mech":"comp","name":"alliteration","patt":"/s/","phon":"ph38","resp":"#AH"},"rf-o5153-702510-1-765566":{"aff":["repetition"],"id":"rf-o5153-702510-1-765566","loc":[{"line":"o5153-l37480","words":"o5153-702510 o5153-702560"}],"mech":"comp","name":"consonance","patt":"/z/","phon":"ph39","resp":"#AH"},"rf-o5153-702510-1-765567":{"aff":["repetition"],"id":"rf-o5153-702510-1-765567","loc":[{"line":"o5153-l37480","words":"o5153-702510 o5153-702540"}],"mech":"comp","name":"consonance","patt":"/s/","phon":"ph38","resp":"#AH"},"rf-o5153-702520-1-750872":{"aff":["repetition"],"id":"rf-o5153-702520-1-750872","loc":[{"line":"o5153-l37480","words":"o5153-702520 o5153-702540"}],"mech":"comp","name":"assonance","patt":"/eɪ/","phon":"ph13","resp":"#AH"},"rf-o5153-702540-1-765568":{"aff":["repetition"],"id":"rf-o5153-702540-1-765568","loc":[{"line":"o5153-l37480","words":"o5153-702540 o5153-702580"}],"mech":"comp","name":"consonance","patt":"/t/","phon":"ph28","resp":"#AH"},"rf-o5153-702600-1-765569":{"aff":["repetition"],"id":"rf-o5153-702600-1-765569","loc":[{"line":"o5153-l37485","words":"o5153-702600 o5153-702610 o5153-702620 o5153-702660"}],"mech":"comp","name":"consonance","patt":"/m/","phon":"ph23","resp":"#AH"},"rf-o5153-702620-1-750873":{"aff":["repetition"],"id":"rf-o5153-702620-1-750873","loc":[{"line":"o5153-l37485","words":"o5153-702620 o5153-702670"}],"mech":"comp","name":"assonance","patt":"/ɪ/","phon":"ph01","resp":"#AH"},"rf-o5153-702620-1-750874":{"aff":["repetition"],"id":"rf-o5153-702620-1-750874","loc":[{"line":"o5153-l37485","words":"o5153-702620 o5153-702640"}],"mech":"comp","name":"assonance","patt":"/æ/","phon":"ph05","resp":"#AH"},"rf-o5153-702620-1-765570":{"aff":["repetition"],"id":"rf-o5153-702620-1-765570","loc":[{"line":"o5153-l37485","words":"o5153-702620 o5153-702670"}],"mech":"comp","name":"consonance","patt":"/r/","phon":"ph45","resp":"#AH"},"rf-o5153-702660-1-765571":{"aff":["repetition"],"id":"rf-o5153-702660-1-765571","loc":[{"line":"o5153-l37485","words":"o5153-702660 o5153-702670"}],"mech":"comp","name":"consonance","patt":"/n/","phon":"ph24","resp":"#AH"}}