<?xml version="1.0" encoding="utf-8"?>
<!DOCTYPE div
  SYSTEM "about:legacy-compat">
<div xmlns:tei="http://www.tei-c.org/ns/1.0"
     xmlns="http://www.tei-c.org/ns/1.0"
     xmlns:ecep="http://www.eighteenthcenturypoetry.org/ns"
     ana="#iamb #pentameter #blankverse #inscription"
     corresp="#txt_AkenMa1721_w0006"
     ecep:syllab="10"
     met="-+|-+|-+|-+|-+/"
     n="3"
     rendition="#lgvspace"
     rhyme=""
     subtype="eceptext"
     type="inscription"
     xml:id="o5157-w0042"
     decls="#semi-normalized">
   <link target="authors.xml#aut_AkenMa1721" type="author"/>
   <link target="27806" type="DMI"/>
   <head type="main">
      <seg resp="#AH">[Inscription] <c> </c>
      </seg>
      <w xml:id="o5157-063920"
         n="33-a-0640"
         ecep:lem="iii"
         ecep:pos="crd"
         ecep:reg="III"
         ecep:spe="III"
         ecep:syllab="1"
         ecep:pron="rˌəʊmənθrˈiː">III</w>
      <pc xml:id="o5157-063930"
          n="33-a-0650"
          unit="sentence"
          ecep:lem="."
          ecep:pos="."
          ecep:reg="."
          ecep:spe=".">.</pc>
   </head>
   <lg>
      <l xml:id="o5157-l03445">
         <w xml:id="o5157-063950"
            n="33-a-0660"
            ecep:lem="whoever"
            ecep:pos="r-crq"
            ecep:reg="WHOEVER"
            ecep:spe="WHOE'ER"
            ecep:syllab="2"
            ecep:pron="huːˈeə">WHOE'ER</w>
         <c> </c>
         <w xml:id="o5157-063960"
            n="33-a-0670"
            ecep:lem="thou"
            ecep:pos="pns21"
            ecep:reg="thou"
            ecep:spe="thou"
            ecep:syllab="1"
            ecep:pron="θaʊ">thou</w>
         <c> </c>
         <w xml:id="o5157-063970"
            n="33-a-0680"
            ecep:lem="be"
            ecep:pos="vb2r"
            ecep:reg="art"
            ecep:spe="art"
            ecep:syllab="1"
            ecep:pron="ɑːt">art</w>
         <c> </c>
         <w xml:id="o5157-063980"
            n="33-a-0690"
            ecep:lem="who"
            ecep:pos="r-crq"
            ecep:reg="whose"
            ecep:spe="whose"
            ecep:syllab="1"
            ecep:pron="huːz">whose</w>
         <c> </c>
         <w xml:id="o5157-063990"
            n="33-a-0700"
            ecep:lem="path"
            ecep:pos="n1"
            ecep:reg="path"
            ecep:spe="path"
            ecep:syllab="1"
            ecep:pron="pɑːθ">path</w>
         <c> </c>
         <w xml:id="o5157-064000"
            n="33-a-0710"
            ecep:lem="in"
            ecep:pos="p-acp"
            ecep:reg="in"
            ecep:spe="in"
            ecep:syllab="1"
            ecep:pron="ɪn">in</w>
         <c> </c>
         <w xml:id="o5157-064010"
            n="33-a-0720"
            ecep:lem="summer"
            ecep:pos="n1"
            ecep:reg="summer"
            ecep:spe="summer"
            ecep:syllab="2"
            ecep:pron="ˈsʌmə">summer</w>
         <c> </c>
         <w xml:id="o5157-064020"
            n="33-a-0730"
            ecep:lem="lie"
            ecep:pos="vvz"
            ecep:reg="lies"
            ecep:spe="lies"
            ecep:syllab="1"
            ecep:pron="laɪz">lies</w>
      </l>
      <l xml:id="o5157-l03450">
         <w xml:id="o5157-064030"
            n="33-a-0740"
            ecep:lem="through"
            ecep:pos="p-acp"
            ecep:reg="Through"
            ecep:spe="Through"
            ecep:syllab="1"
            ecep:pron="θruː">Through</w>
         <c> </c>
         <w xml:id="o5157-064040"
            n="33-a-0750"
            ecep:lem="yonder"
            ecep:pos="d"
            ecep:reg="yonder"
            ecep:spe="yonder"
            ecep:syllab="2"
            ecep:pron="ˈjɒndə">yonder</w>
         <c> </c>
         <w xml:id="o5157-064050"
            n="33-a-0760"
            ecep:lem="village"
            ecep:pos="n1"
            ecep:reg="village"
            ecep:spe="village"
            ecep:syllab="2"
            ecep:pron="ˈvɪlɪdʒ">village</w>
         <pc xml:id="o5157-064060"
             n="33-a-0770"
             ecep:lem=","
             ecep:pos=","
             ecep:reg=","
             ecep:spe=",">,</pc>
         <c> </c>
         <w xml:id="o5157-064070"
            n="33-a-0780"
            ecep:lem="turn"
            ecep:pos="vvb"
            ecep:reg="turn"
            ecep:spe="turn"
            ecep:syllab="1"
            ecep:pron="tɜːn">turn</w>
         <c> </c>
         <w xml:id="o5157-064080"
            n="33-a-0790"
            ecep:lem="thou"
            ecep:pos="pno21"
            ecep:reg="thee"
            ecep:spe="thee"
            ecep:syllab="1"
            ecep:pron="ðiː">thee</w>
         <c> </c>
         <w xml:id="o5157-064090"
            n="33-a-0800"
            ecep:lem="where"
            ecep:pos="c-crq"
            ecep:reg="where"
            ecep:spe="where"
            ecep:syllab="1"
            ecep:pron="weə">where</w>
         <c> </c>
         <w xml:id="o5157-064100"
            n="33-a-0810"
            ecep:lem="the"
            ecep:pos="dt"
            ecep:reg="the"
            ecep:spe="the"
            ecep:syllab="1"
            ecep:pron="ðiː">the</w>
         <c> </c>
         <w xml:id="o5157-064110"
            n="33-a-0820"
            ecep:lem="grove"
            ecep:pos="n1"
            ecep:reg="grove"
            ecep:spe="grove"
            ecep:syllab="1"
            ecep:pron="grəʊv">grove</w>
      </l>
      <l xml:id="o5157-l03455">
         <w xml:id="o5157-064120"
            n="33-a-0830"
            ecep:lem="of"
            ecep:pos="pp-f"
            ecep:reg="Of"
            ecep:spe="Of"
            ecep:syllab="1"
            ecep:pron="ɒv">Of</w>
         <c> </c>
         <w xml:id="o5157-064130"
            n="33-a-0840"
            ecep:lem="branch"
            ecep:pos="j-vvg"
            ecep:reg="branching"
            ecep:spe="branching"
            ecep:syllab="2"
            ecep:pron="brɑːnʃɪŋ">branching</w>
         <c> </c>
         <w xml:id="o5157-064140"
            n="33-a-0850"
            ecep:lem="oak"
            ecep:pos="n2"
            ecep:reg="oaks"
            ecep:spe="oaks"
            ecep:syllab="1"
            ecep:pron="əʊks">oaks</w>
         <c> </c>
         <w xml:id="o5157-064150"
            n="33-a-0860"
            ecep:lem="a"
            ecep:pos="dt"
            ecep:reg="a"
            ecep:spe="a"
            ecep:syllab="1"
            ecep:pron="ə">a</w>
         <c> </c>
         <w xml:id="o5157-064160"
            n="33-a-0870"
            ecep:lem="rural"
            ecep:pos="j"
            ecep:reg="rural"
            ecep:spe="rural"
            ecep:syllab="2"
            ecep:pron="ˈrʊərl">rural</w>
         <c> </c>
         <w xml:id="o5157-064170"
            n="33-a-0880"
            ecep:lem="palace"
            ecep:pos="n1"
            ecep:reg="palace"
            ecep:spe="palace"
            ecep:syllab="2"
            ecep:pron="ˈpælɪs">palace</w>
         <c> </c>
         <w xml:id="o5157-064180"
            n="33-a-0890"
            ecep:lem="old"
            ecep:pos="j"
            ecep:reg="old"
            ecep:spe="old"
            ecep:syllab="1"
            ecep:pron="əʊld">old</w>
      </l>
      <l xml:id="o5157-l03460">
         <w xml:id="o5157-064190"
            n="33-a-0900"
            ecep:lem="imbosom"
            ecep:pos="vvz"
            ecep:reg="Imbosoms"
            ecep:spe="Imbosoms"
            ecep:syllab="3"
            ecep:pron="ɪmbˈɒsəmz">Imbosoms</w>
         <pc xml:id="o5157-064200"
             n="33-a-0910"
             unit="sentence"
             ecep:lem="."
             ecep:pos="."
             ecep:reg="."
             ecep:spe=".">.</pc>
         <c> </c>
         <w xml:id="o5157-064210"
            n="33-a-0920"
            ecep:lem="there"
            ecep:pos="pc-acp"
            ecep:reg="there"
            ecep:spe="there"
            ecep:syllab="1"
            ecep:pron="ðeə">there</w>
         <c> </c>
         <w xml:id="o5157-064220"
            n="33-a-0930"
            ecep:lem="dwell"
            ecep:pos="vvz"
            ecep:reg="dwells"
            ecep:spe="dwells"
            ecep:syllab="1"
            ecep:pron="dwelz">dwells</w>
         <c> </c>
         <w xml:id="o5157-064230"
            n="33-a-0940"
            ecep:lem="Albert"
            ecep:pos="np1"
            ecep:reg="Albert"
            ecep:spe="Albert"
            ecep:syllab="2"
            ecep:pron="ˈælbət">Albert</w>
         <pc xml:id="o5157-064240"
             n="33-a-0950"
             ecep:lem=","
             ecep:pos=","
             ecep:reg=","
             ecep:spe=",">,</pc>
         <c> </c>
         <w xml:id="o5157-064250"
            n="33-a-0960"
            ecep:lem="generous"
            ecep:pos="j"
            ecep:reg="generous"
            ecep:spe="generous"
            ecep:syllab="2"
            ecep:pron="ˈdʒenrəs">generous</w>
         <c> </c>
         <w xml:id="o5157-064260"
            n="33-a-0970"
            ecep:lem="lord"
            ecep:pos="n1"
            ecep:reg="lord"
            ecep:spe="lord"
            ecep:syllab="1"
            ecep:pron="lɔːd">lord</w>
      </l>
      <l xml:id="o5157-l03465">
         <w xml:id="o5157-064270"
            n="33-a-0980"
            ecep:lem="of"
            ecep:pos="pp-f"
            ecep:reg="Of"
            ecep:spe="Of"
            ecep:syllab="1"
            ecep:pron="ɒv">Of</w>
         <c> </c>
         <w xml:id="o5157-064280"
            n="33-a-0990"
            ecep:lem="all"
            ecep:pos="d"
            ecep:reg="all"
            ecep:spe="all"
            ecep:syllab="1"
            ecep:pron="ɔːl">all</w>
         <c> </c>
         <w xml:id="o5157-064290"
            n="33-a-1000"
            ecep:lem="the"
            ecep:pos="dt"
            ecep:reg="the"
            ecep:spe="the"
            ecep:syllab="1"
            ecep:pron="ðiː">the</w>
         <c> </c>
         <w xml:id="o5157-064300"
            n="33-a-1010"
            ecep:lem="harvest"
            ecep:pos="n1"
            ecep:reg="harvest"
            ecep:spe="harvest"
            ecep:syllab="2"
            ecep:pron="ˈhɑːvɪst">harvest</w>
         <c> </c>
         <w xml:id="o5157-064310"
            n="33-a-1020"
            ecep:lem="round"
            ecep:pos="av-j"
            ecep:reg="round"
            ecep:spe="round"
            ecep:syllab="1"
            ecep:pron="raʊnd">round</w>
         <pc xml:id="o5157-064320"
             n="33-a-1030"
             unit="sentence"
             ecep:lem="."
             ecep:pos="."
             ecep:reg="."
             ecep:spe=".">.</pc>
         <c> </c>
         <w xml:id="o5157-064330"
            n="33-a-1040"
            ecep:lem="and"
            ecep:pos="cc"
            ecep:reg="and"
            ecep:spe="and"
            ecep:syllab="1"
            ecep:pron="ænd">and</w>
         <c> </c>
         <w xml:id="o5157-064340"
            n="33-a-1050"
            ecep:lem="onward"
            ecep:pos="av"
            ecep:reg="onward"
            ecep:spe="onward"
            ecep:syllab="2"
            ecep:pron="ˈɒnwəd">onward</w>
         <c> </c>
         <w xml:id="o5157-064350"
            n="33-a-1060"
            ecep:lem="thence"
            ecep:pos="av"
            ecep:reg="thence"
            ecep:spe="thence"
            ecep:syllab="1"
            ecep:pron="ðens">thence</w>
      </l>
      <l xml:id="o5157-l03470">
         <w xml:id="o5157-064360"
            n="33-a-1070"
            ecep:lem="a"
            ecep:pos="dt"
            ecep:reg="A"
            ecep:spe="A"
            ecep:syllab="1"
            ecep:pron="ə">A</w>
         <c> </c>
         <w xml:id="o5157-064370"
            n="33-a-1080"
            ecep:lem="low"
            ecep:pos="j"
            ecep:reg="low"
            ecep:spe="low"
            ecep:syllab="1"
            ecep:pron="ləʊ">low</w>
         <c> </c>
         <w xml:id="o5157-064380"
            n="33-a-1090"
            ecep:lem="plain"
            ecep:pos="j"
            ecep:reg="plain"
            ecep:spe="plain"
            ecep:syllab="1"
            ecep:pron="pleɪn">plain</w>
         <c> </c>
         <w xml:id="o5157-064390"
            n="33-a-1100"
            ecep:lem="chapel"
            ecep:pos="n1"
            ecep:reg="chapel"
            ecep:spe="chapel"
            ecep:syllab="2"
            ecep:pron="ˈtʃæpl">chapel</w>
         <c> </c>
         <w xml:id="o5157-064400"
            n="33-a-1110"
            ecep:lem="front"
            ecep:pos="vvz"
            ecep:reg="fronts"
            ecep:spe="fronts"
            ecep:syllab="1"
            ecep:pron="frʌnts">fronts</w>
         <c> </c>
         <w xml:id="o5157-064410"
            n="33-a-1120"
            ecep:lem="the"
            ecep:pos="dt"
            ecep:reg="the"
            ecep:spe="the"
            ecep:syllab="1"
            ecep:pron="ðiː">the</w>
         <c> </c>
         <w xml:id="o5157-064420"
            n="33-a-1130"
            ecep:lem="morning"
            ecep:pos="n1"
            ecep:reg="morning"
            ecep:spe="morning"
            ecep:syllab="2"
            ecep:pron="ˈmɔːnɪŋ">morning</w>
         <c> </c>
         <w xml:id="o5157-064430"
            n="33-a-1140"
            ecep:lem="light"
            ecep:pos="n1"
            ecep:reg="light"
            ecep:spe="light"
            ecep:syllab="1"
            ecep:pron="laɪt">light</w>
      </l>
      <l xml:id="o5157-l03475">
         <w xml:id="o5157-064440"
            n="33-a-1150"
            ecep:lem="fast"
            ecep:pos="av-j"
            ecep:reg="Fast"
            ecep:spe="Fast"
            ecep:syllab="1"
            ecep:pron="fɑːst">Fast</w>
         <c> </c>
         <w xml:id="o5157-064450"
            n="33-a-1160"
            ecep:lem="by"
            ecep:pos="p-acp"
            ecep:reg="by"
            ecep:spe="by"
            ecep:syllab="1"
            ecep:pron="baɪ">by</w>
         <c> </c>
         <w xml:id="o5157-064460"
            n="33-a-1170"
            ecep:lem="a"
            ecep:pos="dt"
            ecep:reg="a"
            ecep:spe="a"
            ecep:syllab="1"
            ecep:pron="ə">a</w>
         <c> </c>
         <w xml:id="o5157-064470"
            n="33-a-1180"
            ecep:lem="silent"
            ecep:pos="j"
            ecep:reg="silent"
            ecep:spe="silent"
            ecep:syllab="2"
            ecep:pron="ˈsaɪlənt">silent</w>
         <c> </c>
         <w xml:id="o5157-064480"
            n="33-a-1190"
            ecep:lem="rivilet"
            ecep:pos="n1"
            ecep:reg="rivilet"
            ecep:spe="rivilet"
            ecep:syllab="3"
            ecep:pron="rˈɪvɪlət">rivilet</w>
         <pc xml:id="o5157-064490"
             n="33-a-1200"
             unit="sentence"
             ecep:lem="."
             ecep:pos="."
             ecep:reg="."
             ecep:spe=".">.</pc>
         <c> </c>
         <w xml:id="o5157-064500"
            n="33-a-1210"
            ecep:lem="humble"
            ecep:pos="av-j"
            ecep:reg="Humbly"
            ecep:spe="Humbly"
            ecep:syllab="2"
            ecep:pron="ˈhʌmbli">Humbly</w>
         <c> </c>
         <w xml:id="o5157-064510"
            n="33-a-1220"
            ecep:lem="walk"
            ecep:pos="n1"
            ecep:reg="walk"
            ecep:spe="walk"
            ecep:syllab="1"
            ecep:pron="wɔːk">walk</w>
         <pc xml:id="o5157-064520"
             n="33-a-1230"
             ecep:lem=","
             ecep:pos=","
             ecep:reg=","
             ecep:spe=",">,</pc>
      </l>
      <l xml:id="o5157-l03480">
         <w xml:id="o5157-064530"
            n="33-a-1240"
            ecep:lem="o"
            ecep:pos="uh"
            ecep:reg="OH"
            ecep:spe="O"
            ecep:syllab="1"
            ecep:pron="əʊ">O</w>
         <c> </c>
         <w xml:id="o5157-064540"
            n="33-a-1250"
            ecep:lem="stranger"
            ecep:pos="n1"
            ecep:reg="stranger"
            ecep:spe="stranger"
            ecep:syllab="2"
            ecep:pron="ˈstreɪndʒə">stranger</w>
         <pc xml:id="o5157-064550"
             n="33-a-1260"
             ecep:lem=","
             ecep:pos=","
             ecep:reg=","
             ecep:spe=",">,</pc>
         <c> </c>
         <w xml:id="o5157-064560"
            n="33-a-1270"
            ecep:lem="over"
            ecep:pos="p-acp"
            ecep:reg="over"
            ecep:spe="o'er"
            ecep:syllab="1"
            ecep:pron="ˈɔːə">o'er</w>
         <c> </c>
         <w xml:id="o5157-064570"
            n="33-a-1280"
            ecep:lem="the"
            ecep:pos="dt"
            ecep:reg="the"
            ecep:spe="the"
            ecep:syllab="1"
            ecep:pron="ðiː">the</w>
         <c> </c>
         <w xml:id="o5157-064580"
            n="33-a-1290"
            ecep:lem="consecrate"
            ecep:pos="j-vvn"
            ecep:reg="consecrated"
            ecep:spe="consecrated"
            ecep:syllab="4"
            ecep:pron="ˈkɒnsɪkreɪtɪd">consecrated</w>
         <c> </c>
         <w xml:id="o5157-064590"
            n="33-a-1300"
            ecep:lem="ground"
            ecep:pos="n1"
            ecep:reg="ground"
            ecep:spe="ground"
            ecep:syllab="1"
            ecep:pron="graʊnd">ground</w>
         <pc xml:id="o5157-064600"
             n="33-a-1310"
             ecep:lem=";"
             ecep:pos=";"
             ecep:reg=";"
             ecep:spe=";">;</pc>
      </l>
      <l xml:id="o5157-l03485">
         <w xml:id="o5157-064610"
            n="33-a-1320"
            ecep:lem="and"
            ecep:pos="cc"
            ecep:reg="And"
            ecep:spe="And"
            ecep:syllab="1"
            ecep:pron="ænd">And</w>
         <c> </c>
         <w xml:id="o5157-064620"
            n="33-a-1330"
            ecep:lem="on"
            ecep:pos="p-acp"
            ecep:reg="on"
            ecep:spe="on"
            ecep:syllab="1"
            ecep:pron="ɒn">on</w>
         <c> </c>
         <w xml:id="o5157-064630"
            n="33-a-1340"
            ecep:lem="that"
            ecep:pos="d"
            ecep:reg="that"
            ecep:spe="that"
            ecep:syllab="1"
            ecep:pron="ðæt">that</w>
         <c> </c>
         <w xml:id="o5157-064640"
            n="33-a-1350"
            ecep:lem="verdant"
            ecep:pos="j"
            ecep:reg="verdant"
            ecep:spe="verdant"
            ecep:syllab="2"
            ecep:pron="ˈvɜːdnt">verdant</w>
         <c> </c>
         <w xml:id="o5157-064650"
            n="33-a-1360"
            ecep:lem="hilloc"
            ecep:pos="n1"
            ecep:reg="hilloc"
            ecep:spe="hilloc"
            ecep:syllab="2"
            ecep:pron="hˈɪlɒk">hilloc</w>
         <pc xml:id="o5157-064660"
             n="33-a-1370"
             ecep:lem=","
             ecep:pos=","
             ecep:reg=","
             ecep:spe=",">,</pc>
         <c> </c>
         <w xml:id="o5157-064670"
            n="33-a-1380"
            ecep:lem="which"
            ecep:pos="r-crq"
            ecep:reg="which"
            ecep:spe="which"
            ecep:syllab="1"
            ecep:pron="wɪtʃ">which</w>
         <c> </c>
         <w xml:id="o5157-064680"
            n="33-a-1390"
            ecep:lem="thou"
            ecep:pos="pns21"
            ecep:reg="thou"
            ecep:spe="thou"
            ecep:syllab="1"
            ecep:pron="θaʊ">thou</w>
         <c> </c>
         <w xml:id="o5157-064690"
            n="33-a-1400"
            ecep:lem="see"
            ecep:pos="vv2"
            ecep:reg="seest"
            ecep:spe="see'st"
            ecep:syllab="1"
            ecep:pron="siːst">see'st</w>
      </l>
      <l xml:id="o5157-l03490">
         <w xml:id="o5157-064700"
            n="33-a-1410"
            ecep:lem="beset"
            ecep:pos="vvn"
            ecep:reg="Beset"
            ecep:spe="Beset"
            ecep:syllab="2"
            ecep:pron="bɪˈset">Beset</w>
         <c> </c>
         <w xml:id="o5157-064710"
            n="33-a-1420"
            ecep:lem="with"
            ecep:pos="p-acp"
            ecep:reg="with"
            ecep:spe="with"
            ecep:syllab="1"
            ecep:pron="wɪð">with</w>
         <c> </c>
         <w xml:id="o5157-064720"
            n="33-a-1430"
            ecep:lem="osier"
            ecep:pos="n2"
            ecep:reg="osiers"
            ecep:spe="osiers"
            ecep:syllab="2"
            ecep:pron="ˈəʊziəz">osiers</w>
         <pc xml:id="o5157-064730"
             n="33-a-1440"
             ecep:lem=","
             ecep:pos=","
             ecep:reg=","
             ecep:spe=",">,</pc>
         <c> </c>
         <w xml:id="o5157-064740"
            n="33-a-1450"
            ecep:lem="let"
            ecep:pos="vvb"
            ecep:reg="let"
            ecep:spe="let"
            ecep:syllab="1"
            ecep:pron="let">let</w>
         <c> </c>
         <w xml:id="o5157-064750"
            n="33-a-1460"
            ecep:lem="thy"
            ecep:pos="po21"
            ecep:reg="thy"
            ecep:spe="thy"
            ecep:syllab="1"
            ecep:pron="ðaɪ">thy</w>
         <c> </c>
         <w xml:id="o5157-064760"
            n="33-a-1470"
            ecep:lem="pious"
            ecep:pos="j"
            ecep:reg="pious"
            ecep:spe="pious"
            ecep:syllab="2"
            ecep:pron="ˈpaɪəs">pious</w>
         <c> </c>
         <w xml:id="o5157-064770"
            n="33-a-1480"
            ecep:lem="hand"
            ecep:pos="n1"
            ecep:reg="hand"
            ecep:spe="hand"
            ecep:syllab="1"
            ecep:pron="hænd">hand</w>
      </l>
      <l xml:id="o5157-l03495">
         <w xml:id="o5157-064780"
            n="33-a-1490"
            ecep:lem="sprinkle"
            ecep:pos="vvi"
            ecep:reg="Sprinkle"
            ecep:spe="Sprinkle"
            ecep:syllab="2"
            ecep:pron="ˈsprɪŋkl">Sprinkle</w>
         <c> </c>
         <w xml:id="o5157-064790"
            n="33-a-1500"
            ecep:lem="fresh"
            ecep:pos="j"
            ecep:reg="fresh"
            ecep:spe="fresh"
            ecep:syllab="1"
            ecep:pron="freʃ">fresh</w>
         <c> </c>
         <w xml:id="o5157-064800"
            n="33-a-1510"
            ecep:lem="water"
            ecep:pos="n1"
            ecep:reg="water"
            ecep:spe="water"
            ecep:syllab="2"
            ecep:pron="ˈwɔːtə">water</w>
         <c> </c>
         <w xml:id="o5157-064810"
            n="33-a-1520"
            ecep:lem="from"
            ecep:pos="p-acp"
            ecep:reg="from"
            ecep:spe="from"
            ecep:syllab="1"
            ecep:pron="frɒm">from</w>
         <c> </c>
         <w xml:id="o5157-064820"
            n="33-a-1530"
            ecep:lem="the"
            ecep:pos="dt"
            ecep:reg="the"
            ecep:spe="the"
            ecep:syllab="1"
            ecep:pron="ðiː">the</w>
         <c> </c>
         <w xml:id="o5157-064830"
            n="33-a-1540"
            ecep:lem="brook"
            ecep:pos="n1"
            ecep:reg="brook"
            ecep:spe="brook"
            ecep:syllab="1"
            ecep:pron="brʊk">brook</w>
         <c> </c>
         <w xml:id="o5157-064840"
            n="33-a-1550"
            ecep:lem="and"
            ecep:pos="cc"
            ecep:reg="and"
            ecep:spe="and"
            ecep:syllab="1"
            ecep:pron="ænd">and</w>
         <c> </c>
         <w xml:id="o5157-064850"
            n="33-a-1560"
            ecep:lem="strew"
            ecep:pos="vvi"
            ecep:reg="strew"
            ecep:spe="strew"
            ecep:syllab="1"
            ecep:pron="struː">strew</w>
      </l>
      <l xml:id="o5157-l03500">
         <w xml:id="o5157-064860"
            n="33-a-1570"
            ecep:lem="sweet-smelling"
            ecep:pos="j"
            ecep:reg="Sweet-smelling"
            ecep:spe="Sweet-smelling"
            ecep:syllab="3"
            ecep:pron="ˌswiːtˈsmelɪŋ">Sweet-smelling</w>
         <c> </c>
         <w xml:id="o5157-064870"
            n="33-a-1580"
            ecep:lem="flower"
            ecep:pos="n2"
            ecep:reg="flowers"
            ecep:spe="flow'rs"
            ecep:syllab="1"
            ecep:pron="flæəz">flow'rs</w>
         <pc xml:id="o5157-064880"
             n="33-a-1590"
             unit="sentence"
             ecep:lem="."
             ecep:pos="."
             ecep:reg="."
             ecep:spe=".">.</pc>
         <c> </c>
         <w xml:id="o5157-064890"
            n="33-a-1600"
            ecep:lem="for"
            ecep:pos="p-acp"
            ecep:reg="for"
            ecep:spe="for"
            ecep:syllab="1"
            ecep:pron="fɔː">for</w>
         <c> </c>
         <w xml:id="o5157-064900"
            n="33-a-1610"
            ecep:lem="there"
            ecep:pos="a-acp"
            ecep:reg="there"
            ecep:spe="there"
            ecep:syllab="1"
            ecep:pron="ðeə">there</w>
         <c> </c>
         <w xml:id="o5157-064910"
            n="33-a-1620"
            ecep:lem="do"
            ecep:pos="vdz"
            ecep:reg="does"
            ecep:spe="doth"
            ecep:syllab="1"
            ecep:pron="dʌθ">doth</w>
         <c> </c>
         <w xml:id="o5157-064920"
            n="33-a-1630"
            ecep:lem="Edmund"
            ecep:pos="np1"
            ecep:reg="Edmund"
            ecep:spe="Edmund"
            ecep:syllab="2"
            ecep:pron="ˈedmənd">Edmund</w>
         <c> </c>
         <w xml:id="o5157-064930"
            n="33-a-1640"
            ecep:lem="rest"
            ecep:pos="vvi"
            ecep:reg="rest"
            ecep:spe="rest"
            ecep:syllab="1"
            ecep:pron="rest">rest</w>
         <pc xml:id="o5157-064940"
             n="33-a-1650"
             ecep:lem=","
             ecep:pos=","
             ecep:reg=","
             ecep:spe=",">,</pc>
      </l>
      <l xml:id="o5157-l03505">
         <w xml:id="o5157-064950"
            n="33-a-1660"
            ecep:lem="the"
            ecep:pos="dt"
            ecep:reg="The"
            ecep:spe="The"
            ecep:syllab="1"
            ecep:pron="ðiː">The</w>
         <c> </c>
         <w xml:id="o5157-064960"
            n="33-a-1670"
            ecep:lem="learned"
            ecep:pos="j"
            ecep:reg="learnt"
            ecep:spe="learned"
            ecep:syllab="2"
            ecep:pron="ˈlɜːnɪd">learned</w>
         <c> </c>
         <w xml:id="o5157-064970"
            n="33-a-1680"
            ecep:lem="shepherd"
            ecep:pos="n1"
            ecep:reg="shepherd"
            ecep:spe="shepherd"
            ecep:syllab="2"
            ecep:pron="ˈʃepəd">shepherd</w>
         <pc xml:id="o5157-064980"
             n="33-a-1690"
             ecep:lem=";"
             ecep:pos=";"
             ecep:reg=";"
             ecep:spe=";">;</pc>
         <c> </c>
         <w xml:id="o5157-064990"
            n="33-a-1700"
            ecep:lem="for"
            ecep:pos="p-acp"
            ecep:reg="for"
            ecep:spe="for"
            ecep:syllab="1"
            ecep:pron="fɔː">for</w>
         <c> </c>
         <w xml:id="o5157-065000"
            n="33-a-1710"
            ecep:lem="each"
            ecep:pos="d"
            ecep:reg="each"
            ecep:spe="each"
            ecep:syllab="1"
            ecep:pron="iːtʃ">each</w>
         <c> </c>
         <w xml:id="o5157-065010"
            n="33-a-1720"
            ecep:lem="rural"
            ecep:pos="j"
            ecep:reg="rural"
            ecep:spe="rural"
            ecep:syllab="2"
            ecep:pron="ˈrʊərl">rural</w>
         <c> </c>
         <w xml:id="o5157-065020"
            n="33-a-1730"
            ecep:lem="art"
            ecep:pos="n1"
            ecep:reg="art"
            ecep:spe="art"
            ecep:syllab="1"
            ecep:pron="ɑːt">art</w>
      </l>
      <l xml:id="o5157-l03510">
         <w xml:id="o5157-065030"
            n="33-a-1740"
            ecep:lem="famed"
            ecep:pos="n1"
            ecep:reg="Famed"
            ecep:spe="Fam'd"
            ecep:syllab="1"
            ecep:pron="feɪmd">Fam'd</w>
         <pc xml:id="o5157-065040"
             n="33-a-1750"
             ecep:lem=","
             ecep:pos=","
             ecep:reg=","
             ecep:spe=",">,</pc>
         <c> </c>
         <w xml:id="o5157-065050"
            n="33-a-1760"
            ecep:lem="and"
            ecep:pos="cc"
            ecep:reg="and"
            ecep:spe="and"
            ecep:syllab="1"
            ecep:pron="ænd">and</w>
         <c> </c>
         <w xml:id="o5157-065060"
            n="33-a-1770"
            ecep:lem="for"
            ecep:pos="p-acp"
            ecep:reg="for"
            ecep:spe="for"
            ecep:syllab="1"
            ecep:pron="fɔː">for</w>
         <c> </c>
         <w xml:id="o5157-065070"
            n="33-a-1780"
            ecep:lem="song"
            ecep:pos="n2"
            ecep:reg="songs"
            ecep:spe="songs"
            ecep:syllab="1"
            ecep:pron="sɒŋz">songs</w>
         <c> </c>
         <w xml:id="o5157-065080"
            n="33-a-1790"
            ecep:lem="harmonious"
            ecep:pos="j"
            ecep:reg="harmonious"
            ecep:spe="harmonious"
            ecep:syllab="4"
            ecep:pron="hɑːˈməʊniəs">harmonious</w>
         <pc xml:id="o5157-065090"
             n="33-a-1800"
             ecep:lem=","
             ecep:pos=","
             ecep:reg=","
             ecep:spe=",">,</pc>
         <c> </c>
         <w xml:id="o5157-065100"
            n="33-a-1810"
            ecep:lem="and"
            ecep:pos="cc"
            ecep:reg="and"
            ecep:spe="and"
            ecep:syllab="1"
            ecep:pron="ænd">and</w>
         <c> </c>
         <w xml:id="o5157-065110"
            n="33-a-1820"
            ecep:lem="the"
            ecep:pos="dt"
            ecep:reg="the"
            ecep:spe="the"
            ecep:syllab="1"
            ecep:pron="ðiː">the</w>
         <c> </c>
         <w xml:id="o5157-065120"
            n="33-a-1830"
            ecep:lem="woe"
            ecep:pos="n2"
            ecep:reg="woes"
            ecep:spe="woes"
            ecep:syllab="1"
            ecep:pron="wəʊz">woes</w>
      </l>
      <l xml:id="o5157-l03515">
         <w xml:id="o5157-065130"
            n="33-a-1840"
            ecep:lem="of"
            ecep:pos="pp-f"
            ecep:reg="Of"
            ecep:spe="Of"
            ecep:syllab="1"
            ecep:pron="ɒv">Of</w>
         <c> </c>
         <w xml:id="o5157-065140"
            n="33-a-1850"
            ecep:lem="ill-requited"
            ecep:pos="j"
            ecep:reg="ill-requited"
            ecep:spe="ill-requited"
            ecep:syllab="4"
            ecep:pron="ɪlˌrɪˈkwaɪtɪd">ill-requited</w>
         <c> </c>
         <w xml:id="o5157-065150"
            n="33-a-1860"
            ecep:lem="love"
            ecep:pos="n1"
            ecep:reg="love"
            ecep:spe="love"
            ecep:syllab="1"
            ecep:pron="lʌv">love</w>
         <pc xml:id="o5157-065160"
             n="33-a-1870"
             unit="sentence"
             ecep:lem="."
             ecep:pos="."
             ecep:reg="."
             ecep:spe=".">.</pc>
         <c> </c>
         <w xml:id="o5157-065170"
            n="33-a-1880"
            ecep:lem="the"
            ecep:pos="dt"
            ecep:reg="The"
            ecep:spe="The"
            ecep:syllab="1"
            ecep:pron="ðiː">The</w>
         <c> </c>
         <w xml:id="o5157-065180"
            n="33-a-1890"
            ecep:lem="faithless"
            ecep:pos="j"
            ecep:reg="faithless"
            ecep:spe="faithless"
            ecep:syllab="2"
            ecep:pron="ˈfeɪθləs">faithless</w>
         <c> </c>
         <w xml:id="o5157-065190"
            n="33-a-1900"
            ecep:lem="pride"
            ecep:pos="n1"
            ecep:reg="pride"
            ecep:spe="pride"
            ecep:syllab="1"
            ecep:pron="praɪd">pride</w>
      </l>
      <l xml:id="o5157-l03520">
         <w xml:id="o5157-065200"
            n="33-a-1910"
            ecep:lem="of"
            ecep:pos="pp-f"
            ecep:reg="Of"
            ecep:spe="Of"
            ecep:syllab="1"
            ecep:pron="ɒv">Of</w>
         <c> </c>
         <w xml:id="o5157-065210"
            n="33-a-1920"
            ecep:lem="fair"
            ecep:pos="j"
            ecep:reg="fair"
            ecep:spe="fair"
            ecep:syllab="1"
            ecep:pron="feə">fair</w>
         <c> </c>
         <w xml:id="o5157-065220"
            n="33-a-1930"
            ecep:lem="Matilda"
            ecep:pos="np1"
            ecep:reg="Matilda"
            ecep:spe="Matilda"
            ecep:syllab="3"
            ecep:pron="məˈtɪldə">Matilda</w>
         <c> </c>
         <w xml:id="o5157-065230"
            n="33-a-1940"
            ecep:lem="sink"
            ecep:pos="vvd"
            ecep:reg="sank"
            ecep:spe="sank"
            ecep:syllab="1"
            ecep:pron="sæŋk">sank</w>
         <c> </c>
         <w xml:id="o5157-065240"
            n="33-a-1950"
            ecep:lem="he"
            ecep:pos="pno31"
            ecep:reg="him"
            ecep:spe="him"
            ecep:syllab="1"
            ecep:pron="hɪm">him</w>
         <c> </c>
         <w xml:id="o5157-065250"
            n="33-a-1960"
            ecep:lem="to"
            ecep:pos="p-acp"
            ecep:reg="to"
            ecep:spe="to"
            ecep:syllab="1"
            ecep:pron="tuː">to</w>
         <c> </c>
         <w xml:id="o5157-065260"
            n="33-a-1970"
            ecep:lem="the"
            ecep:pos="dt"
            ecep:reg="the"
            ecep:spe="the"
            ecep:syllab="1"
            ecep:pron="ðiː">the</w>
         <c> </c>
         <w xml:id="o5157-065270"
            n="33-a-1980"
            ecep:lem="grave"
            ecep:pos="n1"
            ecep:reg="grave"
            ecep:spe="grave"
            ecep:syllab="1"
            ecep:pron="grɑːv">grave</w>
      </l>
      <pb facs="o5157/0037_L" n="32" rend="none"/>
      <l xml:id="o5157-l03525">
         <w xml:id="o5157-065280"
            n="34-a-0010"
            ecep:lem="in"
            ecep:pos="p-acp"
            ecep:reg="In"
            ecep:spe="In"
            ecep:syllab="1"
            ecep:pron="ɪn">In</w>
         <c> </c>
         <w xml:id="o5157-065290"
            n="34-a-0020"
            ecep:lem="manhood"
            ecep:pos="ng1"
            ecep:reg="manhood's"
            ecep:spe="manhood's"
            ecep:syllab="2"
            ecep:pron="ˈmænhʊdz">manhood's</w>
         <c> </c>
         <w xml:id="o5157-065300"
            n="34-a-0030"
            ecep:lem="prime"
            ecep:pos="j-jn"
            ecep:reg="prime"
            ecep:spe="prime"
            ecep:syllab="1"
            ecep:pron="praɪm">prime</w>
         <pc xml:id="o5157-065310"
             n="34-a-0040"
             unit="sentence"
             ecep:lem="."
             ecep:pos="."
             ecep:reg="."
             ecep:spe=".">.</pc>
         <c> </c>
         <w xml:id="o5157-065320"
            n="34-a-0050"
            ecep:lem="but"
            ecep:pos="p-acp"
            ecep:reg="But"
            ecep:spe="But"
            ecep:syllab="1"
            ecep:pron="bʌt">But</w>
         <c> </c>
         <w xml:id="o5157-065330"
            n="34-a-0060"
            ecep:lem="soon"
            ecep:pos="av"
            ecep:reg="soon"
            ecep:spe="soon"
            ecep:syllab="1"
            ecep:pron="suːn">soon</w>
         <c> </c>
         <w xml:id="o5157-065340"
            n="34-a-0070"
            ecep:lem="do"
            ecep:pos="vdd"
            ecep:reg="did"
            ecep:spe="did"
            ecep:syllab="1"
            ecep:pron="dɪd">did</w>
         <c> </c>
         <w xml:id="o5157-065350"
            n="34-a-0080"
            ecep:lem="righteous"
            ecep:pos="j"
            ecep:reg="righteous"
            ecep:spe="righteous"
            ecep:syllab="2"
            ecep:pron="ˈraɪtʃəs">righteous</w>
         <c> </c>
         <w xml:id="o5157-065360"
            n="34-a-0090"
            ecep:lem="heaven"
            ecep:pos="n1"
            ecep:reg="heaven"
            ecep:spe="heaven"
            ecep:syllab="1"
            ecep:pron="ˈhevn">heaven</w>
      </l>
      <l xml:id="o5157-l03530">
         <w xml:id="o5157-065370"
            n="34-a-0100"
            ecep:lem="with"
            ecep:pos="p-acp"
            ecep:reg="With"
            ecep:spe="With"
            ecep:syllab="1"
            ecep:pron="wɪð">With</w>
         <c> </c>
         <w xml:id="o5157-065380"
            n="34-a-0110"
            ecep:lem="tear"
            ecep:pos="n2"
            ecep:reg="tears"
            ecep:spe="tears"
            ecep:syllab="1"
            ecep:pron="tɪəz">tears</w>
         <pc xml:id="o5157-065390"
             n="34-a-0120"
             ecep:lem=","
             ecep:pos=","
             ecep:reg=","
             ecep:spe=",">,</pc>
         <c> </c>
         <w xml:id="o5157-065400"
            n="34-a-0130"
            ecep:lem="with"
            ecep:pos="p-acp"
            ecep:reg="with"
            ecep:spe="with"
            ecep:syllab="1"
            ecep:pron="wɪð">with</w>
         <c> </c>
         <w xml:id="o5157-065410"
            n="34-a-0140"
            ecep:lem="sharp"
            ecep:pos="j"
            ecep:reg="sharp"
            ecep:spe="sharp"
            ecep:syllab="1"
            ecep:pron="ʃɑːp">sharp</w>
         <c> </c>
         <w xml:id="o5157-065420"
            n="34-a-0150"
            ecep:lem="remorse"
            ecep:pos="n1"
            ecep:reg="remorse"
            ecep:spe="remorse"
            ecep:syllab="2"
            ecep:pron="rɪˈmɔːs">remorse</w>
         <pc xml:id="o5157-065430"
             n="34-a-0160"
             ecep:lem=","
             ecep:pos=","
             ecep:reg=","
             ecep:spe=",">,</pc>
         <c> </c>
         <w xml:id="o5157-065440"
            n="34-a-0170"
            ecep:lem="and"
            ecep:pos="cc"
            ecep:reg="and"
            ecep:spe="and"
            ecep:syllab="1"
            ecep:pron="ænd">and</w>
         <c> </c>
         <w xml:id="o5157-065450"
            n="34-a-0180"
            ecep:lem="pine"
            ecep:pos="j-vvg"
            ecep:reg="pining"
            ecep:spe="pining"
            ecep:syllab="2"
            ecep:pron="paɪnɪŋ">pining</w>
         <c> </c>
         <w xml:id="o5157-065460"
            n="34-a-0190"
            ecep:lem="care"
            ecep:pos="n1"
            ecep:reg="care"
            ecep:spe="care"
            ecep:syllab="1"
            ecep:pron="keə">care</w>
         <pc xml:id="o5157-065470"
             n="34-a-0200"
             ecep:lem=","
             ecep:pos=","
             ecep:reg=","
             ecep:spe=",">,</pc>
      </l>
      <l xml:id="o5157-l03535">
         <w xml:id="o5157-065480"
            n="34-a-0210"
            ecep:lem="avenge"
            ecep:pos="vvb"
            ecep:reg="Avenge"
            ecep:spe="Avenge"
            ecep:syllab="2"
            ecep:pron="əˈvendʒ">Avenge</w>
         <c> </c>
         <w xml:id="o5157-065490"
            n="34-a-0220"
            ecep:lem="her"
            ecep:pos="po31"
            ecep:reg="her"
            ecep:spe="her"
            ecep:syllab="1"
            ecep:pron="hɜː">her</w>
         <c> </c>
         <w xml:id="o5157-065500"
            n="34-a-0230"
            ecep:lem="falsehood"
            ecep:pos="n1"
            ecep:reg="falsehood"
            ecep:spe="falshood"
            ecep:syllab="2"
            ecep:pron="ˈfɔːlshʊd">falshood</w>
         <pc xml:id="o5157-065510"
             n="34-a-0240"
             unit="sentence"
             ecep:lem="."
             ecep:pos="."
             ecep:reg="."
             ecep:spe=".">.</pc>
         <c> </c>
         <w xml:id="o5157-065520"
            n="34-a-0250"
            ecep:lem="nor"
            ecep:pos="ccx"
            ecep:reg="nor"
            ecep:spe="nor"
            ecep:syllab="1"
            ecep:pron="nɔː">nor</w>
         <c> </c>
         <w xml:id="o5157-065530"
            n="34-a-0260"
            ecep:lem="can"
            ecep:pos="vmd"
            ecep:reg="could"
            ecep:spe="could"
            ecep:syllab="1"
            ecep:pron="kʊd">could</w>
         <c> </c>
         <w xml:id="o5157-065540"
            n="34-a-0270"
            ecep:lem="all"
            ecep:pos="d"
            ecep:reg="all"
            ecep:spe="all"
            ecep:syllab="1"
            ecep:pron="ɔːl">all</w>
         <c> </c>
         <w xml:id="o5157-065550"
            n="34-a-0280"
            ecep:lem="the"
            ecep:pos="dt"
            ecep:reg="the"
            ecep:spe="the"
            ecep:syllab="1"
            ecep:pron="ðiː">the</w>
         <c> </c>
         <w xml:id="o5157-065560"
            n="34-a-0290"
            ecep:lem="gold"
            ecep:pos="n1"
            ecep:reg="gold"
            ecep:spe="gold"
            ecep:syllab="1"
            ecep:pron="gəʊld">gold</w>
      </l>
      <l xml:id="o5157-l03540">
         <w xml:id="o5157-065570"
            n="34-a-0300"
            ecep:lem="and"
            ecep:pos="cc"
            ecep:reg="And"
            ecep:spe="And"
            ecep:syllab="1"
            ecep:pron="ænd">And</w>
         <c> </c>
         <w xml:id="o5157-065580"
            n="34-a-0310"
            ecep:lem="nuptial"
            ecep:pos="j-jn"
            ecep:reg="nuptial"
            ecep:spe="nuptial"
            ecep:syllab="2"
            ecep:pron="ˈnʌpʃl">nuptial</w>
         <c> </c>
         <w xml:id="o5157-065590"
            n="34-a-0320"
            ecep:lem="pomp"
            ecep:pos="n1"
            ecep:reg="pomp"
            ecep:spe="pomp"
            ecep:syllab="1"
            ecep:pron="pɒmp">pomp</w>
         <pc xml:id="o5157-065600"
             n="34-a-0330"
             ecep:lem=","
             ecep:pos=","
             ecep:reg=","
             ecep:spe=",">,</pc>
         <c> </c>
         <w xml:id="o5157-065610"
            n="34-a-0340"
            ecep:lem="which"
            ecep:pos="r-crq"
            ecep:reg="which"
            ecep:spe="which"
            ecep:syllab="1"
            ecep:pron="wɪtʃ">which</w>
         <c> </c>
         <w xml:id="o5157-065620"
            n="34-a-0350"
            ecep:lem="lure"
            ecep:pos="vvd"
            ecep:reg="lured"
            ecep:spe="lur'd"
            ecep:syllab="1"
            ecep:pron="lʊəd">lur'd</w>
         <c> </c>
         <w xml:id="o5157-065630"
            n="34-a-0360"
            ecep:lem="her"
            ecep:pos="po31"
            ecep:reg="her"
            ecep:spe="her"
            ecep:syllab="1"
            ecep:pron="hɜː">her</w>
         <c> </c>
         <w xml:id="o5157-065640"
            n="34-a-0370"
            ecep:lem="plight"
            ecep:pos="j-vvn"
            ecep:reg="plighted"
            ecep:spe="plighted"
            ecep:syllab="2"
            ecep:pron="plaɪtɪd">plighted</w>
         <c> </c>
         <w xml:id="o5157-065650"
            n="34-a-0380"
            ecep:lem="faith"
            ecep:pos="n1"
            ecep:reg="faith"
            ecep:spe="faith"
            ecep:syllab="1"
            ecep:pron="feɪθ">faith</w>
      </l>
      <l xml:id="o5157-l03545">
         <w xml:id="o5157-065660"
            n="34-a-0390"
            ecep:lem="from"
            ecep:pos="p-acp"
            ecep:reg="From"
            ecep:spe="From"
            ecep:syllab="1"
            ecep:pron="frɒm">From</w>
         <c> </c>
         <w xml:id="o5157-065670"
            n="34-a-0400"
            ecep:lem="Edmund"
            ecep:pos="np1"
            ecep:reg="Edmund"
            ecep:spe="Edmund"
            ecep:syllab="2"
            ecep:pron="ˈedmənd">Edmund</w>
         <c> </c>
         <w xml:id="o5157-065680"
            n="34-a-0410"
            ecep:lem="to"
            ecep:pos="p-acp"
            ecep:reg="to"
            ecep:spe="to"
            ecep:syllab="1"
            ecep:pron="tuː">to</w>
         <c> </c>
         <w xml:id="o5157-065690"
            n="34-a-0420"
            ecep:lem="a"
            ecep:pos="dt"
            ecep:reg="a"
            ecep:spe="a"
            ecep:syllab="1"
            ecep:pron="ə">a</w>
         <c> </c>
         <w xml:id="o5157-065700"
            n="34-a-0430"
            ecep:lem="lofty"
            ecep:pos="jc"
            ecep:reg="loftier"
            ecep:spe="loftier"
            ecep:syllab="3"
            ecep:pron="ˈlɒftiə">loftier</w>
         <c> </c>
         <w xml:id="o5157-065710"
            n="34-a-0440"
            ecep:lem="husband"
            ecep:pos="ng1"
            ecep:reg="husband's"
            ecep:spe="husband's"
            ecep:syllab="2"
            ecep:pron="ˈhʌzbəndz">husband's</w>
         <c> </c>
         <w xml:id="o5157-065720"
            n="34-a-0450"
            ecep:lem="home"
            ecep:pos="n1-an"
            ecep:reg="home"
            ecep:spe="home"
            ecep:syllab="1"
            ecep:pron="həʊm">home</w>
         <pc xml:id="o5157-065730"
             n="34-a-0460"
             ecep:lem=","
             ecep:pos=","
             ecep:reg=","
             ecep:spe=",">,</pc>
      </l>
      <l xml:id="o5157-l03550">
         <w xml:id="o5157-065740"
            n="34-a-0470"
            ecep:lem="relieve"
            ecep:pos="vvb"
            ecep:reg="Relieve"
            ecep:spe="Relieve"
            ecep:syllab="2"
            ecep:pron="rɪˈliːv">Relieve</w>
         <c> </c>
         <w xml:id="o5157-065750"
            n="34-a-0480"
            ecep:lem="she"
            ecep:pos="pno31"
            ecep:reg="her"
            ecep:spe="her"
            ecep:syllab="1"
            ecep:pron="hɜː">her</w>
         <c> </c>
         <w xml:id="o5157-065760"
            n="34-a-0490"
            ecep:lem="break"
            ecep:pos="vvg"
            ecep:reg="breaking"
            ecep:spe="breaking"
            ecep:syllab="2"
            ecep:pron="breɪkɪŋ">breaking</w>
         <c> </c>
         <w xml:id="o5157-065770"
            n="34-a-0500"
            ecep:lem="heart"
            ecep:pos="n1"
            ecep:reg="heart"
            ecep:spe="heart"
            ecep:syllab="1"
            ecep:pron="hɑːt">heart</w>
         <pc xml:id="o5157-065780"
             n="34-a-0510"
             ecep:lem=","
             ecep:pos=","
             ecep:reg=","
             ecep:spe=",">,</pc>
         <c> </c>
         <w xml:id="o5157-065790"
            n="34-a-0520"
            ecep:lem="or"
            ecep:pos="cc"
            ecep:reg="or"
            ecep:spe="or"
            ecep:syllab="1"
            ecep:pron="ɔː">or</w>
         <c> </c>
         <w xml:id="o5157-065800"
            n="34-a-0530"
            ecep:lem="turn"
            ecep:pos="vvi"
            ecep:reg="turn"
            ecep:spe="turn"
            ecep:syllab="1"
            ecep:pron="tɜːn">turn</w>
         <c> </c>
         <w xml:id="o5157-065810"
            n="34-a-0540"
            ecep:lem="aside"
            ecep:pos="av"
            ecep:reg="aside"
            ecep:spe="aside"
            ecep:syllab="2"
            ecep:pron="əˈsaɪd">aside</w>
      </l>
      <l xml:id="o5157-l03555">
         <w xml:id="o5157-065820"
            n="34-a-0550"
            ecep:lem="the"
            ecep:pos="dt"
            ecep:reg="The"
            ecep:spe="The"
            ecep:syllab="1"
            ecep:pron="ðiː">The</w>
         <c> </c>
         <w xml:id="o5157-065830"
            n="34-a-0560"
            ecep:lem="stroke"
            ecep:pos="n2"
            ecep:reg="strokes"
            ecep:spe="strokes"
            ecep:syllab="1"
            ecep:pron="strəʊks">strokes</w>
         <c> </c>
         <w xml:id="o5157-065840"
            n="34-a-0570"
            ecep:lem="of"
            ecep:pos="pp-f"
            ecep:reg="of"
            ecep:spe="of"
            ecep:syllab="1"
            ecep:pron="ɒv">of</w>
         <c> </c>
         <w xml:id="o5157-065850"
            n="34-a-0580"
            ecep:lem="death"
            ecep:pos="n1"
            ecep:reg="death"
            ecep:spe="death"
            ecep:syllab="1"
            ecep:pron="deθ">death</w>
         <pc xml:id="o5157-065860"
             n="34-a-0590"
             unit="sentence"
             ecep:lem="."
             ecep:pos="."
             ecep:reg="."
             ecep:spe=".">.</pc>
         <c> </c>
         <w xml:id="o5157-065870"
            n="34-a-0600"
            ecep:lem="go"
            ecep:pos="vvb"
            ecep:reg="Go"
            ecep:spe="Go"
            ecep:syllab="1"
            ecep:pron="gəʊ">Go</w>
         <pc xml:id="o5157-065880"
             n="34-a-0610"
             ecep:lem=","
             ecep:pos=","
             ecep:reg=","
             ecep:spe=",">,</pc>
         <c> </c>
         <w xml:id="o5157-065890"
            n="34-a-0620"
            ecep:lem="traveller"
            ecep:pos="n1"
            ecep:reg="traveller"
            ecep:spe="traveller"
            ecep:syllab="3"
            ecep:pron="ˈtrævlə">traveller</w>
         <pc xml:id="o5157-065900"
             n="34-a-0630"
             ecep:lem=";"
             ecep:pos=";"
             ecep:reg=";"
             ecep:spe=";">;</pc>
         <c> </c>
         <w xml:id="o5157-065910"
            n="34-a-0640"
            ecep:lem="relate"
            ecep:pos="vvb"
            ecep:reg="relate"
            ecep:spe="relate"
            ecep:syllab="2"
            ecep:pron="rɪˈleɪt">relate</w>
      </l>
      <l xml:id="o5157-l03560">
         <w xml:id="o5157-065920"
            n="34-a-0650"
            ecep:lem="the"
            ecep:pos="dt"
            ecep:reg="The"
            ecep:spe="The"
            ecep:syllab="1"
            ecep:pron="ðiː">The</w>
         <c> </c>
         <w xml:id="o5157-065930"
            n="34-a-0660"
            ecep:lem="mournful"
            ecep:pos="j"
            ecep:reg="mournful"
            ecep:spe="mournful"
            ecep:syllab="2"
            ecep:pron="ˈmɔːnfl">mournful</w>
         <c> </c>
         <w xml:id="o5157-065940"
            n="34-a-0670"
            ecep:lem="story"
            ecep:pos="n1"
            ecep:reg="storey"
            ecep:spe="story"
            ecep:syllab="2"
            ecep:pron="ˈstɔːri">story</w>
         <pc xml:id="o5157-065950"
             n="34-a-0680"
             unit="sentence"
             ecep:lem="."
             ecep:pos="."
             ecep:reg="."
             ecep:spe=".">.</pc>
         <c> </c>
         <w xml:id="o5157-065960"
            n="34-a-0690"
            ecep:lem="haply"
            ecep:pos="av"
            ecep:reg="haply"
            ecep:spe="haply"
            ecep:syllab="2"
            ecep:pron="ˈhæpli">haply</w>
         <c> </c>
         <w xml:id="o5157-065970"
            n="34-a-0700"
            ecep:lem="some"
            ecep:pos="d"
            ecep:reg="some"
            ecep:spe="some"
            ecep:syllab="1"
            ecep:pron="sʌm">some</w>
         <c> </c>
         <w xml:id="o5157-065980"
            n="34-a-0710"
            ecep:lem="fair"
            ecep:pos="j"
            ecep:reg="fair"
            ecep:spe="fair"
            ecep:syllab="1"
            ecep:pron="feə">fair</w>
         <c> </c>
         <w xml:id="o5157-065990"
            n="34-a-0720"
            ecep:lem="maid"
            ecep:pos="n1"
            ecep:reg="maid"
            ecep:spe="maid"
            ecep:syllab="1"
            ecep:pron="meɪd">maid</w>
      </l>
      <l xml:id="o5157-l03565">
         <w xml:id="o5157-066000"
            n="34-a-0730"
            ecep:lem="may"
            ecep:pos="vmb"
            ecep:reg="May"
            ecep:spe="May"
            ecep:syllab="1"
            ecep:pron="meɪ">May</w>
         <c> </c>
         <w xml:id="o5157-066010"
            n="34-a-0740"
            ecep:lem="hold"
            ecep:pos="vvi"
            ecep:reg="hold"
            ecep:spe="hold"
            ecep:syllab="1"
            ecep:pron="həʊld">hold</w>
         <c> </c>
         <w xml:id="o5157-066020"
            n="34-a-0750"
            ecep:lem="it"
            ecep:pos="pn31"
            ecep:reg="it"
            ecep:spe="it"
            ecep:syllab="1"
            ecep:pron="ɪt">it</w>
         <c> </c>
         <w xml:id="o5157-066030"
            n="34-a-0760"
            ecep:lem="in"
            ecep:pos="p-acp"
            ecep:reg="in"
            ecep:spe="in"
            ecep:syllab="1"
            ecep:pron="ɪn">in</w>
         <c> </c>
         <w xml:id="o5157-066040"
            n="34-a-0770"
            ecep:lem="remembrance"
            ecep:pos="n1"
            ecep:reg="remembrance"
            ecep:spe="remembrance"
            ecep:syllab="3"
            ecep:pron="rɪˈmembrns">remembrance</w>
         <pc xml:id="o5157-066050"
             n="34-a-0780"
             ecep:lem=","
             ecep:pos=","
             ecep:reg=","
             ecep:spe=",">,</pc>
         <c> </c>
         <w xml:id="o5157-066060"
            n="34-a-0790"
            ecep:lem="and"
            ecep:pos="cc"
            ecep:reg="and"
            ecep:spe="and"
            ecep:syllab="1"
            ecep:pron="ænd">and</w>
         <c> </c>
         <w xml:id="o5157-066070"
            n="34-a-0800"
            ecep:lem="be"
            ecep:pos="vbi"
            ecep:reg="be"
            ecep:spe="be"
            ecep:syllab="1"
            ecep:pron="biː">be</w>
         <c> </c>
         <w xml:id="o5157-066080"
            n="34-a-0810"
            ecep:lem="teach"
            ecep:pos="vvn"
            ecep:reg="taught"
            ecep:spe="taught"
            ecep:syllab="1"
            ecep:pron="tɔːt">taught</w>
      </l>
      <l xml:id="o5157-l03570">
         <w xml:id="o5157-066090"
            n="34-a-0820"
            ecep:lem="that"
            ecep:pos="d"
            ecep:reg="That"
            ecep:spe="That"
            ecep:syllab="1"
            ecep:pron="ðæt">That</w>
         <c> </c>
         <w xml:id="o5157-066100"
            n="34-a-0830"
            ecep:lem="riches"
            ecep:pos="n2"
            ecep:reg="riches"
            ecep:spe="riches"
            ecep:syllab="2"
            ecep:pron="rɪtʃɪz">riches</w>
         <c> </c>
         <w xml:id="o5157-066110"
            n="34-a-0840"
            ecep:lem="can"
            ecep:pos="vmbx"
            ecep:reg="cannot"
            ecep:spe="cannot"
            ecep:syllab="2"
            ecep:pron="ˈkænɒt">cannot</w>
         <c> </c>
         <w xml:id="o5157-066120"
            n="34-a-0850"
            ecep:lem="pay"
            ecep:pos="vvi"
            ecep:reg="pay"
            ecep:spe="pay"
            ecep:syllab="1"
            ecep:pron="peɪ">pay</w>
         <c> </c>
         <w xml:id="o5157-066130"
            n="34-a-0860"
            ecep:lem="for"
            ecep:pos="p-acp"
            ecep:reg="for"
            ecep:spe="for"
            ecep:syllab="1"
            ecep:pron="fɔː">for</w>
         <c> </c>
         <w xml:id="o5157-066140"
            n="34-a-0870"
            ecep:lem="truth"
            ecep:pos="n1"
            ecep:reg="truth"
            ecep:spe="truth"
            ecep:syllab="1"
            ecep:pron="truːθ">truth</w>
         <c> </c>
         <w xml:id="o5157-066150"
            n="34-a-0880"
            ecep:lem="or"
            ecep:pos="cc"
            ecep:reg="or"
            ecep:spe="or"
            ecep:syllab="1"
            ecep:pron="ɔː">or</w>
         <c> </c>
         <w xml:id="o5157-066160"
            n="34-a-0890"
            ecep:lem="love"
            ecep:pos="n1"
            ecep:reg="love"
            ecep:spe="love"
            ecep:syllab="1"
            ecep:pron="lʌv">love</w>
         <pc xml:id="o5157-066170"
             n="34-a-0900"
             unit="sentence"
             ecep:lem="."
             ecep:pos="."
             ecep:reg="."
             ecep:spe=".">.</pc>
      </l>
   </lg>
</div>
