<?xml version="1.0" encoding="utf-8"?>
<!DOCTYPE div
  >
<div xmlns:ecep="http://www.eighteenthcenturypoetry.org/ns"
     xmlns="http://www.tei-c.org/ns/1.0"
     xmlns:tei="http://www.tei-c.org/ns/1.0"
     ana="#iamb #pentameter #couplet #heroiccouplet #pair #paraphrase"
     corresp="#txt_WillHe1759_w0059"
     decls="#semi-normalized"
     ecep:syllab="10"
     met="-+|-+|-+|-+|-+/"
     rendition="#lgvspace"
     rhyme="aa"
     subtype="eceptext"
     type="poem"
     xml:id="bhw18-w0590">
   <link target="authors.xml#aut_WillHe1759" type="author"/>
   <head type="main">
      <w xml:id="bhw18-489490"
         n="a-0010"
         ecep:lem="paraphrase"
         ecep:pos="vvb"
         ecep:reg="PARAPHRASE"
         ecep:spe="PARAPHRASE"
         ecep:syllab="3"
         ecep:pron="ˈpærəfreɪz">PARAPHRASE</w>
      <pc xml:id="bhw18-489500"
          n="a-0020"
          unit="sentence"
          ecep:lem="."
          ecep:pos="."
          ecep:reg="."
          ecep:spe=".">.</pc>
   </head>
   <epigraph>
      <q>
         <c> </c>
         <pc xml:id="bhw18-489540"
             n="a-0030"
             ecep:lem="&#34;"
             ecep:pos="&#34;"
             ecep:reg="&#34;"
             ecep:spe="&#34;">"</pc>
         <w xml:id="bhw18-489550"
            n="a-0040"
            ecep:lem="that"
            ecep:pos="cst"
            ecep:reg="That"
            ecep:spe="That"
            ecep:syllab="1"
            ecep:pron="ðæt">That</w>
         <c> </c>
         <w xml:id="bhw18-489560"
            n="a-0050"
            ecep:lem="thy"
            ecep:pos="po21"
            ecep:reg="thine"
            ecep:spe="thine"
            ecep:syllab="1"
            ecep:pron="ðaɪn">thine</w>
         <c> </c>
         <w xml:id="bhw18-489570"
            n="a-0060"
            ecep:lem="alm"
            ecep:pos="n2"
            ecep:reg="alms"
            ecep:spe="alms"
            ecep:syllab="1"
            ecep:pron="ɑːmz">alms</w>
         <c> </c>
         <w xml:id="bhw18-489580"
            n="a-0070"
            ecep:lem="may"
            ecep:pos="vmb"
            ecep:reg="may"
            ecep:spe="may"
            ecep:syllab="1"
            ecep:pron="meɪ">may</w>
         <c> </c>
         <w xml:id="bhw18-489590"
            n="a-0080"
            ecep:lem="be"
            ecep:pos="vbi"
            ecep:reg="be"
            ecep:spe="be"
            ecep:syllab="1"
            ecep:pron="biː">be</w>
         <c> </c>
         <w xml:id="bhw18-489600"
            n="a-0090"
            ecep:lem="in"
            ecep:pos="p-acp"
            ecep:reg="in"
            ecep:spe="in"
            ecep:syllab="1"
            ecep:pron="ɪn">in</w>
         <c> </c>
         <w xml:id="bhw18-489610"
            n="a-0100"
            ecep:lem="secret"
            ecep:pos="n-jn"
            ecep:reg="secret"
            ecep:spe="secret"
            ecep:syllab="2"
            ecep:pron="ˈsiːkrət">secret</w>
         <pc xml:id="bhw18-489620"
             n="a-0110"
             ecep:lem=","
             ecep:pos=","
             ecep:reg=","
             ecep:spe=",">,</pc>
         <lb/>
         <c> </c>
         <w xml:id="bhw18-489630"
            n="a-0120"
            ecep:lem="and"
            ecep:pos="cc"
            ecep:reg="and"
            ecep:spe="and"
            ecep:syllab="1"
            ecep:pron="ænd">and</w>
         <c> </c>
         <w xml:id="bhw18-489640"
            n="a-0130"
            ecep:lem="thy"
            ecep:pos="po21"
            ecep:reg="thy"
            ecep:spe="thy"
            ecep:syllab="1"
            ecep:pron="ðaɪ">thy</w>
         <c> </c>
         <w xml:id="bhw18-489650"
            n="a-0140"
            ecep:lem="father"
            ecep:pos="n1"
            ecep:reg="Father"
            ecep:spe="Father"
            ecep:syllab="2"
            ecep:pron="ˈfɑːðə">Father</w>
         <c> </c>
         <w xml:id="bhw18-489660"
            n="a-0150"
            ecep:lem="which"
            ecep:pos="r-crq"
            ecep:reg="which"
            ecep:spe="which"
            ecep:syllab="1"
            ecep:pron="wɪtʃ">which</w>
         <c> </c>
         <w xml:id="bhw18-489670"
            n="a-0160"
            ecep:lem="see"
            ecep:pos="vvz"
            ecep:reg="sees"
            ecep:spe="seeth"
            ecep:syllab="1"
            ecep:pron="sˈiːθ">seeth</w>
         <c> </c>
         <w xml:id="bhw18-489680"
            n="a-0170"
            ecep:lem="in"
            ecep:pos="p-acp"
            ecep:reg="in"
            ecep:spe="in"
            ecep:syllab="1"
            ecep:pron="ɪn">in</w>
         <c> </c>
         <w xml:id="bhw18-489690"
            n="a-0180"
            ecep:lem="secret"
            ecep:pos="n-jn"
            ecep:reg="secret"
            ecep:spe="secret"
            ecep:syllab="2"
            ecep:pron="ˈsiːkrət">secret</w>
         <pc xml:id="bhw18-489700"
             n="a-0190"
             ecep:lem=","
             ecep:pos=","
             ecep:reg=","
             ecep:spe=",">,</pc>
         <c> </c>
         <w xml:id="bhw18-489710"
            n="a-0200"
            ecep:lem="himself"
            ecep:pos="px31"
            ecep:reg="himself"
            ecep:spe="himself"
            ecep:syllab="2"
            ecep:pron="hɪmˈself">himself</w>
         <c> </c>
         <w xml:id="bhw18-489720"
            n="a-0210"
            ecep:lem="shall"
            ecep:pos="vmb"
            ecep:reg="shall"
            ecep:spe="shall"
            ecep:syllab="1"
            ecep:pron="ʃæl">shall</w>
         <c> </c>
         <w xml:id="bhw18-489730"
            n="a-0220"
            ecep:lem="reward"
            ecep:pos="vvi"
            ecep:reg="reward"
            ecep:spe="reward"
            ecep:syllab="2"
            ecep:pron="rɪˈwɔːd">reward</w>
         <c> </c>
         <w xml:id="bhw18-489740"
            n="a-0230"
            ecep:lem="thou"
            ecep:pos="pno21"
            ecep:reg="thee"
            ecep:spe="thee"
            ecep:syllab="1"
            ecep:pron="ðiː">thee</w>
         <c> </c>
         <w xml:id="bhw18-489750"
            n="a-0240"
            ecep:lem="open"
            ecep:pos="av-j"
            ecep:reg="openly"
            ecep:spe="openly"
            ecep:syllab="3"
            ecep:pron="ˈəʊpnli">openly</w>
         <pc xml:id="bhw18-489760"
             n="a-0250"
             ecep:lem="."
             ecep:pos="."
             ecep:reg="."
             ecep:spe=".">.</pc>
         <pc xml:id="bhw18-489770"
             n="a-0260"
             unit="sentence"
             ecep:lem="&#34;"
             ecep:pos="&#34;"
             ecep:reg="&#34;"
             ecep:spe="&#34;">"</pc>
      </q>
      <bibl>
         <pc xml:id="bhw18-489800"
             n="a-0270"
             unit="sentence"
             ecep:lem="—"
             ecep:pos="—"
             ecep:reg="—"
             ecep:spe="—">—</pc>
         <c> </c>
         <hi>
            <w xml:id="bhw18-489810"
               n="a-0280"
               ecep:lem="Matt."
               ecep:pos="np1"
               ecep:reg="Matt."
               ecep:spe="Matt."
               ecep:syllab="1"
               ecep:pron="mˈæt">Matt.</w>
         </hi>
         <c> </c>
         <w xml:id="bhw18-489820"
            n="a-0290"
            ecep:lem="vi"
            ecep:pos="crd"
            ecep:reg="VI"
            ecep:spe="VI"
            ecep:syllab="1"
            ecep:pron="ˈvaɪ">VI</w>
         <pc xml:id="bhw18-489830"
             n="a-0300"
             unit="sentence"
             ecep:lem="."
             ecep:pos="."
             ecep:reg="."
             ecep:spe=".">.</pc>
         <c> </c>
         <w xml:id="bhw18-489840"
            n="a-0310"
            ecep:lem="4."
            ecep:pos="crd"
            ecep:reg="4."
            ecep:spe="4."
            ecep:syllab="1"
            ecep:pron="fˈɔː">4.</w>
         <pc unit="sentence" xml:id="bhw18-489840-eos" n="a-0320"/>
      </bibl>
   </epigraph>
   <lg xml:id="bhw18-s01835">
      <l xml:id="bhw18-l21230">
         <hi rendition="#sc">
            <w xml:id="bhw18-489870"
               n="a-0330"
               ecep:lem="hear"
               ecep:pos="vvb"
               ecep:reg="HEAR"
               ecep:spe="HEAR"
               ecep:syllab="1"
               ecep:pron="hɪə">HEAR</w>
         </hi>
         <c> </c>
         <w xml:id="bhw18-489880"
            n="a-0340"
            ecep:lem="heaven"
            ecep:pos="ng1"
            ecep:reg="heaven's"
            ecep:spe="heav'n's"
            ecep:syllab="1"
            ecep:pron="ˈhevnz">heav'n's</w>
         <c> </c>
         <w xml:id="bhw18-489890"
            n="a-0350"
            ecep:lem="pure"
            ecep:pos="j"
            ecep:reg="pure"
            ecep:spe="pure"
            ecep:syllab="1"
            ecep:pron="pjʊə">pure</w>
         <c> </c>
         <w xml:id="bhw18-489900"
            n="a-0360"
            ecep:lem="dictate"
            ecep:pos="n2"
            ecep:reg="dictates"
            ecep:spe="dictates"
            ecep:syllab="2"
            ecep:pron="ˈdɪkteɪts">dictates</w>
         <pc xml:id="bhw18-489910"
             n="a-0370"
             ecep:lem=","
             ecep:pos=","
             ecep:reg=","
             ecep:spe=",">,</pc>
         <c> </c>
         <w xml:id="bhw18-489920"
            n="a-0380"
            ecep:lem="you"
            ecep:pos="pn22"
            ecep:reg="you"
            ecep:spe="ye"
            ecep:syllab="1"
            ecep:pron="jiː">ye</w>
         <c> </c>
         <w xml:id="bhw18-489930"
            n="a-0390"
            ecep:lem="presumptuous"
            ecep:pos="j"
            ecep:reg="presumptuous"
            ecep:spe="presumptuous"
            ecep:syllab="4"
            ecep:pron="prɪˈzʌmptʃuəs">presumptuous</w>
         <c> </c>
         <w xml:id="bhw18-489940"
            n="a-0400"
            ecep:lem="crowd"
            ecep:pos="n1"
            ecep:reg="crowd"
            ecep:spe="crowd"
            ecep:syllab="1"
            ecep:pron="kraʊd">crowd</w>
         <pc xml:id="bhw18-489950"
             n="a-0410"
             ecep:lem=","
             ecep:pos=","
             ecep:reg=","
             ecep:spe=",">,</pc>
      </l>
      <l xml:id="bhw18-l21235">
         <c> </c>
         <w xml:id="bhw18-489960"
            n="a-0420"
            ecep:lem="be"
            ecep:pos="vbb"
            ecep:reg="Be"
            ecep:spe="Be"
            ecep:syllab="1"
            ecep:pron="biː">Be</w>
         <c> </c>
         <w xml:id="bhw18-489970"
            n="a-0430"
            ecep:lem="kind"
            ecep:pos="j"
            ecep:reg="kind"
            ecep:spe="kind"
            ecep:syllab="1"
            ecep:pron="kaɪnd">kind</w>
         <c> </c>
         <w xml:id="bhw18-489980"
            n="a-0440"
            ecep:lem="you"
            ecep:pos="pn22"
            ecep:reg="you"
            ecep:spe="ye"
            ecep:syllab="1"
            ecep:pron="jiː">ye</w>
         <c> </c>
         <w xml:id="bhw18-489990"
            n="a-0450"
            ecep:lem="selfish"
            ecep:pos="j"
            ecep:reg="selfish"
            ecep:spe="selfish"
            ecep:syllab="2"
            ecep:pron="ˈselfɪʃ">selfish</w>
         <pc xml:id="bhw18-490000"
             n="a-0460"
             ecep:lem=","
             ecep:pos=","
             ecep:reg=","
             ecep:spe=",">,</pc>
         <c> </c>
         <w xml:id="bhw18-490010"
            n="a-0470"
            ecep:lem="and"
            ecep:pos="cc"
            ecep:reg="and"
            ecep:spe="and"
            ecep:syllab="1"
            ecep:pron="ænd">and</w>
         <c> </c>
         <w xml:id="bhw18-490020"
            n="a-0480"
            ecep:lem="abash"
            ecep:pos="vvd"
            ecep:reg="abashed"
            ecep:spe="abash'd"
            ecep:syllab="2"
            ecep:pron="əˈbæʃt">abash'd</w>
         <c> </c>
         <w xml:id="bhw18-490030"
            n="a-0490"
            ecep:lem="you"
            ecep:pos="pn22"
            ecep:reg="you"
            ecep:spe="ye"
            ecep:syllab="1"
            ecep:pron="jiː">ye</w>
         <c> </c>
         <w xml:id="bhw18-490040"
            n="a-0500"
            ecep:lem="proud"
            ecep:pos="j"
            ecep:reg="proud"
            ecep:spe="proud"
            ecep:syllab="1"
            ecep:pron="praʊd">proud</w>
         <pc xml:id="bhw18-490050"
             n="a-0510"
             unit="sentence"
             ecep:lem="!"
             ecep:pos="!"
             ecep:reg="!"
             ecep:spe="!">!</pc>
         <c> </c>
      </l>
      <l xml:id="bhw18-l21240">
         <w xml:id="bhw18-490060"
            n="a-0520"
            ecep:lem="nor"
            ecep:pos="ccx"
            ecep:reg="Nor"
            ecep:spe="Nor"
            ecep:syllab="1"
            ecep:pron="nɔː">Nor</w>
         <c> </c>
         <w xml:id="bhw18-490070"
            n="a-0530"
            ecep:lem="think"
            ecep:pos="vvb"
            ecep:reg="think"
            ecep:spe="think"
            ecep:syllab="1"
            ecep:pron="θɪŋk">think</w>
         <c> </c>
         <w xml:id="bhw18-490080"
            n="a-0540"
            ecep:lem="the"
            ecep:pos="dt"
            ecep:reg="the"
            ecep:spe="the"
            ecep:syllab="1"
            ecep:pron="ðiː">the</w>
         <c> </c>
         <w xml:id="bhw18-490090"
            n="a-0550"
            ecep:lem="ostentatious"
            ecep:pos="j"
            ecep:reg="ostentatious"
            ecep:spe="ostentatious"
            ecep:syllab="4"
            ecep:pron="ˌɒstenˈteɪʃəs">ostentatious</w>
         <c> </c>
         <w xml:id="bhw18-490100"
            n="a-0560"
            ecep:lem="act"
            ecep:pos="n1"
            ecep:reg="act"
            ecep:spe="act"
            ecep:syllab="1"
            ecep:pron="ækt">act</w>
         <pc xml:id="bhw18-490110"
             n="a-0570"
             ecep:lem=","
             ecep:pos=","
             ecep:reg=","
             ecep:spe=",">,</pc>
         <c> </c>
         <w xml:id="bhw18-490120"
            n="a-0580"
            ecep:lem="which"
            ecep:pos="r-crq"
            ecep:reg="which"
            ecep:spe="which"
            ecep:syllab="1"
            ecep:pron="wɪtʃ">which</w>
         <c> </c>
         <w xml:id="bhw18-490130"
            n="a-0590"
            ecep:lem="draw"
            ecep:pos="vvz"
            ecep:reg="draws"
            ecep:spe="draws"
            ecep:syllab="1"
            ecep:pron="drɔːz">draws</w>
      </l>
      <l xml:id="bhw18-l21245">
         <c> </c>
         <w xml:id="bhw18-490140"
            n="a-0600"
            ecep:lem="the"
            ecep:pos="dt"
            ecep:reg="The"
            ecep:spe="The"
            ecep:syllab="1"
            ecep:pron="ðiː">The</w>
         <c> </c>
         <w xml:id="bhw18-490150"
            n="a-0610"
            ecep:lem="incense"
            ecep:pos="n1"
            ecep:reg="incense"
            ecep:spe="incense"
            ecep:syllab="2"
            ecep:pron="ˈɪnsens">incense</w>
         <c> </c>
         <w xml:id="bhw18-490160"
            n="a-0620"
            ecep:lem="of"
            ecep:pos="pp-f"
            ecep:reg="of"
            ecep:spe="of"
            ecep:syllab="1"
            ecep:pron="ɒv">of</w>
         <c> </c>
         <w xml:id="bhw18-490170"
            n="a-0630"
            ecep:lem="ill"
            ecep:pos="n-jn"
            ecep:reg="ill"
            ecep:spe="ill"
            ecep:syllab="1"
            ecep:pron="ɪl">ill</w>
         <c> </c>
         <w xml:id="bhw18-490180"
            n="a-0640"
            ecep:lem="judge"
            ecep:pos="vvg"
            ecep:reg="judging"
            ecep:spe="judging"
            ecep:syllab="2"
            ecep:pron="dʒʌdʒɪŋ">judging</w>
         <c> </c>
         <w xml:id="bhw18-490190"
            n="a-0650"
            ecep:lem="man"
            ecep:pos="ng1"
            ecep:reg="man's"
            ecep:spe="man's"
            ecep:syllab="1"
            ecep:pron="ˈmænz">man's</w>
         <c> </c>
         <w xml:id="bhw18-490200"
            n="a-0660"
            ecep:lem="applause"
            ecep:pos="n1"
            ecep:reg="applause"
            ecep:spe="applause"
            ecep:syllab="2"
            ecep:pron="əˈplɔːz">applause</w>
         <pc xml:id="bhw18-490210"
             n="a-0670"
             ecep:lem=","
             ecep:pos=","
             ecep:reg=","
             ecep:spe=",">,</pc>
      </l>
      <l xml:id="bhw18-l21250">
         <c> </c>
         <w xml:id="bhw18-490220"
            n="a-0680"
            ecep:lem="the"
            ecep:pos="dt"
            ecep:reg="The"
            ecep:spe="The"
            ecep:syllab="1"
            ecep:pron="ðiː">The</w>
         <c> </c>
         <w xml:id="bhw18-490230"
            n="a-0690"
            ecep:lem="boon"
            ecep:pos="n1"
            ecep:reg="boon"
            ecep:spe="boon"
            ecep:syllab="1"
            ecep:pron="buːn">boon</w>
         <c> </c>
         <w xml:id="bhw18-490240"
            n="a-0700"
            ecep:lem="obtrude"
            ecep:pos="vvn"
            ecep:reg="obtruded"
            ecep:spe="obtruded"
            ecep:syllab="3"
            ecep:pron="əbˈtruːdɪd">obtruded</w>
         <c> </c>
         <w xml:id="bhw18-490250"
            n="a-0710"
            ecep:lem="on"
            ecep:pos="p-acp"
            ecep:reg="on"
            ecep:spe="on"
            ecep:syllab="1"
            ecep:pron="ɒn">on</w>
         <c> </c>
         <w xml:id="bhw18-490260"
            n="a-0720"
            ecep:lem="the"
            ecep:pos="dt"
            ecep:reg="the"
            ecep:spe="the"
            ecep:syllab="1"
            ecep:pron="ðiː">the</w>
         <c> </c>
         <w xml:id="bhw18-490270"
            n="a-0730"
            ecep:lem="gazer"
            ecep:pos="ng1"
            ecep:reg="gazer's"
            ecep:spe="gazer's"
            ecep:syllab="2"
            ecep:pron="geɪzəz">gazer's</w>
         <c> </c>
         <w xml:id="bhw18-490280"
            n="a-0740"
            ecep:lem="sight"
            ecep:pos="n1"
            ecep:reg="sight"
            ecep:spe="sight"
            ecep:syllab="1"
            ecep:pron="saɪt">sight</w>
         <pc xml:id="bhw18-490290"
             n="a-0750"
             ecep:lem=","
             ecep:pos=","
             ecep:reg=","
             ecep:spe=",">,</pc>
      </l>
      <l xml:id="bhw18-l21255">
         <c> </c>
         <w xml:id="bhw18-490300"
            n="a-0760"
            ecep:lem="outweigh"
            ecep:pos="vvz"
            ecep:reg="Outweighs"
            ecep:spe="Outweighs"
            ecep:syllab="2"
            ecep:pron="ˌaʊtˈweɪz">Outweighs</w>
         <c> </c>
         <w xml:id="bhw18-490310"
            n="a-0770"
            ecep:lem="in"
            ecep:pos="p-acp"
            ecep:reg="in"
            ecep:spe="in"
            ecep:syllab="1"
            ecep:pron="ɪn">in</w>
         <c> </c>
         <w xml:id="bhw18-490320"
            n="a-0780"
            ecep:lem="virtue"
            ecep:pos="ng1"
            ecep:reg="virtue's"
            ecep:spe="virtue's"
            ecep:syllab="2"
            ecep:pron="ˈvɜːtʃuːz">virtue's</w>
         <c> </c>
         <w xml:id="bhw18-490330"
            n="a-0790"
            ecep:lem="scale"
            ecep:pos="n1"
            ecep:reg="scale"
            ecep:spe="scale"
            ecep:syllab="1"
            ecep:pron="skeɪl">scale</w>
         <pc xml:id="bhw18-490340"
             n="a-0800"
             ecep:lem=","
             ecep:pos=","
             ecep:reg=","
             ecep:spe=",">,</pc>
         <c> </c>
         <w xml:id="bhw18-490350"
            n="a-0810"
            ecep:lem="the"
            ecep:pos="dt"
            ecep:reg="the"
            ecep:spe="the"
            ecep:syllab="1"
            ecep:pron="ðiː">the</w>
         <c> </c>
         <w xml:id="bhw18-490360"
            n="a-0820"
            ecep:lem="widow"
            ecep:pos="ng1"
            ecep:reg="widow's"
            ecep:spe="widow's"
            ecep:syllab="2"
            ecep:pron="ˈwɪdəʊz">widow's</w>
         <c> </c>
         <w xml:id="bhw18-490370"
            n="a-0830"
            ecep:lem="mite"
            ecep:pos="n1"
            ecep:reg="mite"
            ecep:spe="mite"
            ecep:syllab="1"
            ecep:pron="maɪt">mite</w>
         <pc xml:id="bhw18-490380"
             n="a-0840"
             ecep:lem=";"
             ecep:pos=";"
             ecep:reg=";"
             ecep:spe=";">;</pc>
      </l>
      <l xml:id="bhw18-l21260">
         <c> </c>
         <w xml:id="bhw18-490390"
            n="a-0850"
            ecep:lem="claim"
            ecep:pos="vvb"
            ecep:reg="Claim"
            ecep:spe="Claim"
            ecep:syllab="1"
            ecep:pron="kleɪm">Claim</w>
         <c> </c>
         <w xml:id="bhw18-490400"
            n="a-0860"
            ecep:lem="not"
            ecep:pos="xx"
            ecep:reg="not"
            ecep:spe="not"
            ecep:syllab="1"
            ecep:pron="nɒt">not</w>
         <c> </c>
         <w xml:id="bhw18-490410"
            n="a-0870"
            ecep:lem="in"
            ecep:pos="p-acp"
            ecep:reg="in"
            ecep:spe="in"
            ecep:syllab="1"
            ecep:pron="ɪn">in</w>
         <c> </c>
         <w xml:id="bhw18-490420"
            n="a-0880"
            ecep:lem="his"
            ecep:pos="po31"
            ecep:reg="His"
            ecep:spe="His"
            ecep:syllab="1"
            ecep:pron="hɪz">His</w>
         <c> </c>
         <w xml:id="bhw18-490430"
            n="a-0890"
            ecep:lem="divine"
            ecep:pos="j-jn"
            ecep:reg="divine"
            ecep:spe="divine"
            ecep:syllab="2"
            ecep:pron="dɪˈvaɪn">divine</w>
         <c> </c>
         <w xml:id="bhw18-490440"
            n="a-0900"
            ecep:lem="reward"
            ecep:pos="n2"
            ecep:reg="rewards"
            ecep:spe="rewards"
            ecep:syllab="2"
            ecep:pron="rɪˈwɔːdz">rewards</w>
         <pc xml:id="bhw18-490450"
             n="a-0910"
             ecep:lem=","
             ecep:pos=","
             ecep:reg=","
             ecep:spe=",">,</pc>
         <c> </c>
         <w xml:id="bhw18-490460"
            n="a-0920"
            ecep:lem="a"
            ecep:pos="dt"
            ecep:reg="a"
            ecep:spe="a"
            ecep:syllab="1"
            ecep:pron="ə">a</w>
         <c> </c>
         <w xml:id="bhw18-490470"
            n="a-0930"
            ecep:lem="part"
            ecep:pos="n1"
            ecep:reg="part"
            ecep:spe="part"
            ecep:syllab="1"
            ecep:pron="pɑːt">part</w>
         <pc xml:id="bhw18-490480"
             n="a-0940"
             ecep:lem=","
             ecep:pos=","
             ecep:reg=","
             ecep:spe=",">,</pc>
      </l>
      <l xml:id="bhw18-l21265">
         <c> </c>
         <w xml:id="bhw18-490490"
            n="a-0950"
            ecep:lem="who"
            ecep:pos="q-crq"
            ecep:reg="Who"
            ecep:spe="Who"
            ecep:syllab="1"
            ecep:pron="huː">Who</w>
         <c> </c>
         <w xml:id="bhw18-490500"
            n="a-0960"
            ecep:lem="know"
            ecep:pos="vvz"
            ecep:reg="knows"
            ecep:spe="knows"
            ecep:syllab="1"
            ecep:pron="nəʊz">knows</w>
         <c> </c>
         <w xml:id="bhw18-490510"
            n="a-0970"
            ecep:lem="the"
            ecep:pos="dt"
            ecep:reg="the"
            ecep:spe="the"
            ecep:syllab="1"
            ecep:pron="ðiː">the</w>
         <c> </c>
         <w xml:id="bhw18-490520"
            n="a-0980"
            ecep:lem="motive"
            ecep:pos="n1"
            ecep:reg="motive"
            ecep:spe="motive"
            ecep:syllab="2"
            ecep:pron="ˈməʊtɪv">motive</w>
         <pc xml:id="bhw18-490530"
             n="a-0990"
             ecep:lem=","
             ecep:pos=","
             ecep:reg=","
             ecep:spe=",">,</pc>
         <c> </c>
         <w xml:id="bhw18-490540"
            n="a-1000"
            ecep:lem="and"
            ecep:pos="cc"
            ecep:reg="and"
            ecep:spe="and"
            ecep:syllab="1"
            ecep:pron="ænd">and</w>
         <c> </c>
         <w xml:id="bhw18-490550"
            n="a-1010"
            ecep:lem="who"
            ecep:pos="r-crq"
            ecep:reg="who"
            ecep:spe="who"
            ecep:syllab="1"
            ecep:pron="huː">who</w>
         <c> </c>
         <w xml:id="bhw18-490560"
            n="a-1020"
            ecep:lem="view"
            ecep:pos="vvz"
            ecep:reg="views"
            ecep:spe="views"
            ecep:syllab="1"
            ecep:pron="vjuːz">views</w>
         <c> </c>
         <w xml:id="bhw18-490570"
            n="a-1030"
            ecep:lem="the"
            ecep:pos="dt"
            ecep:reg="the"
            ecep:spe="the"
            ecep:syllab="1"
            ecep:pron="ðiː">the</w>
         <c> </c>
         <w xml:id="bhw18-490580"
            n="a-1040"
            ecep:lem="heart"
            ecep:pos="n1"
            ecep:reg="heart"
            ecep:spe="heart"
            ecep:syllab="1"
            ecep:pron="hɑːt">heart</w>
         <pc xml:id="bhw18-490590"
             n="a-1050"
             ecep:lem=";"
             ecep:pos=";"
             ecep:reg=";"
             ecep:spe=";">;</pc>
      </l>
      <pb facs="bhw18/0338" n="292" rend="none"/>
      <l xml:id="bhw18-l21270">
         <c> </c>
         <w xml:id="bhw18-490600"
            n="a-0010"
            ecep:lem="be"
            ecep:pos="vbb"
            ecep:reg="Be"
            ecep:spe="Be"
            ecep:syllab="1"
            ecep:pron="biː">Be</w>
         <c> </c>
         <w xml:id="bhw18-490610"
            n="a-0020"
            ecep:lem="you"
            ecep:pos="png22"
            ecep:reg="yours"
            ecep:spe="yours"
            ecep:syllab="1"
            ecep:pron="jɔːz">yours</w>
         <c> </c>
         <w xml:id="bhw18-490620"
            n="a-0030"
            ecep:lem="to"
            ecep:pos="pc-acp"
            ecep:reg="to"
            ecep:spe="to"
            ecep:syllab="1"
            ecep:pron="tuː">to</w>
         <c> </c>
         <w xml:id="bhw18-490630"
            n="a-0040"
            ecep:lem="hear"
            ecep:pos="vvi"
            ecep:reg="hear"
            ecep:spe="hear"
            ecep:syllab="1"
            ecep:pron="hɪə">hear</w>
         <c> </c>
         <w xml:id="bhw18-490640"
            n="a-0050"
            ecep:lem="the"
            ecep:pos="dt"
            ecep:reg="the"
            ecep:spe="the"
            ecep:syllab="1"
            ecep:pron="ðiː">the</w>
         <c> </c>
         <w xml:id="bhw18-490650"
            n="a-0060"
            ecep:lem="empty"
            ecep:pos="j"
            ecep:reg="empty"
            ecep:spe="empty"
            ecep:syllab="2"
            ecep:pron="ˈemti">empty</w>
         <c> </c>
         <w xml:id="bhw18-490660"
            n="a-0070"
            ecep:lem="accent"
            ecep:pos="n2"
            ecep:reg="accents"
            ecep:spe="accents"
            ecep:syllab="2"
            ecep:pron="ˈæksnts">accents</w>
         <c> </c>
         <w xml:id="bhw18-490670"
            n="a-0080"
            ecep:lem="roll"
            ecep:pos="vvi"
            ecep:reg="roll"
            ecep:spe="roll"
            ecep:syllab="1"
            ecep:pron="rəʊl">roll</w>
      </l>
      <l xml:id="bhw18-l21275">
         <c> </c>
         <w xml:id="bhw18-490680"
            n="a-0090"
            ecep:lem="of"
            ecep:pos="pp-f"
            ecep:reg="Of"
            ecep:spe="Of"
            ecep:syllab="1"
            ecep:pron="ɒv">Of</w>
         <c> </c>
         <w xml:id="bhw18-490690"
            n="a-0100"
            ecep:lem="praise"
            ecep:pos="n1"
            ecep:reg="praise"
            ecep:spe="praise"
            ecep:syllab="1"
            ecep:pron="preɪz">praise</w>
         <pc xml:id="bhw18-490700"
             n="a-0110"
             ecep:lem=","
             ecep:pos=","
             ecep:reg=","
             ecep:spe=",">,</pc>
         <c> </c>
         <w xml:id="bhw18-490710"
            n="a-0120"
            ecep:lem="reject"
            ecep:pos="vvn"
            ecep:reg="rejected"
            ecep:spe="rejected"
            ecep:syllab="3"
            ecep:pron="rɪˈdʒektɪd">rejected</w>
         <c> </c>
         <w xml:id="bhw18-490720"
            n="a-0130"
            ecep:lem="by"
            ecep:pos="p-acp"
            ecep:reg="by"
            ecep:spe="by"
            ecep:syllab="1"
            ecep:pron="baɪ">by</w>
         <c> </c>
         <w xml:id="bhw18-490730"
            n="a-0140"
            ecep:lem="the"
            ecep:pos="dt"
            ecep:reg="the"
            ecep:spe="the"
            ecep:syllab="1"
            ecep:pron="ðiː">the</w>
         <c> </c>
         <w xml:id="bhw18-490740"
            n="a-0150"
            ecep:lem="conscious"
            ecep:pos="j"
            ecep:reg="conscious"
            ecep:spe="conscious"
            ecep:syllab="2"
            ecep:pron="ˈkɒnʃəs">conscious</w>
         <c> </c>
         <w xml:id="bhw18-490750"
            n="a-0160"
            ecep:lem="soul"
            ecep:pos="n1"
            ecep:reg="soul"
            ecep:spe="soul"
            ecep:syllab="1"
            ecep:pron="səʊl">soul</w>
         <pc xml:id="bhw18-490760"
             n="a-0170"
             unit="sentence"
             ecep:lem="."
             ecep:pos="."
             ecep:reg="."
             ecep:spe=".">.</pc>
         <c> </c>
      </l>
      <l xml:id="bhw18-l21280">
         <w xml:id="bhw18-490770"
            n="a-0180"
            ecep:lem="but"
            ecep:pos="p-acp"
            ecep:reg="But"
            ecep:spe="But"
            ecep:syllab="1"
            ecep:pron="bʌt">But</w>
         <c> </c>
         <w xml:id="bhw18-490780"
            n="a-0190"
            ecep:lem="you"
            ecep:pos="pn22"
            ecep:reg="you"
            ecep:spe="ye"
            ecep:syllab="1"
            ecep:pron="jiː">ye</w>
         <pc xml:id="bhw18-490790"
             n="a-0200"
             ecep:lem=","
             ecep:pos=","
             ecep:reg=","
             ecep:spe=",">,</pc>
         <c> </c>
         <w xml:id="bhw18-490800"
            n="a-0210"
            ecep:lem="who"
            ecep:pos="r-crq"
            ecep:reg="who"
            ecep:spe="who"
            ecep:syllab="1"
            ecep:pron="huː">who</w>
         <c> </c>
         <w xml:id="bhw18-490810"
            n="a-0220"
            ecep:lem="when"
            ecep:pos="c-crq"
            ecep:reg="when"
            ecep:spe="when"
            ecep:syllab="1"
            ecep:pron="wen">when</w>
         <c> </c>
         <w xml:id="bhw18-490820"
            n="a-0230"
            ecep:lem="to"
            ecep:pos="p-acp"
            ecep:reg="to"
            ecep:spe="to"
            ecep:syllab="1"
            ecep:pron="tuː">to</w>
         <c> </c>
         <w xml:id="bhw18-490830"
            n="a-0240"
            ecep:lem="succour"
            ecep:pos="n1"
            ecep:reg="succour"
            ecep:spe="succour"
            ecep:syllab="2"
            ecep:pron="ˈsʌkə">succour</w>
         <c> </c>
         <w xml:id="bhw18-490840"
            n="a-0250"
            ecep:lem="want"
            ecep:pos="vvb"
            ecep:reg="want"
            ecep:spe="want"
            ecep:syllab="1"
            ecep:pron="wɒnt">want</w>
         <c> </c>
         <w xml:id="bhw18-490850"
            n="a-0260"
            ecep:lem="you"
            ecep:pos="pn22"
            ecep:reg="you"
            ecep:spe="ye"
            ecep:syllab="1"
            ecep:pron="jiː">ye</w>
         <c> </c>
         <w xml:id="bhw18-490860"
            n="a-0270"
            ecep:lem="fly"
            ecep:pos="vvb"
            ecep:reg="fly"
            ecep:spe="fly"
            ecep:syllab="1"
            ecep:pron="flaɪ">fly</w>
         <pc xml:id="bhw18-490870"
             n="a-0280"
             ecep:lem=","
             ecep:pos=","
             ecep:reg=","
             ecep:spe=",">,</pc>
      </l>
      <l xml:id="bhw18-l21285">
         <c> </c>
         <w xml:id="bhw18-490880"
            n="a-0290"
            ecep:lem="have"
            ecep:pos="vhb"
            ecep:reg="Have"
            ecep:spe="Have"
            ecep:syllab="1"
            ecep:pron="hæv">Have</w>
         <c> </c>
         <w xml:id="bhw18-490890"
            n="a-0300"
            ecep:lem="never"
            ecep:pos="av-x"
            ecep:reg="never"
            ecep:spe="never"
            ecep:syllab="2"
            ecep:pron="ˈnevə">never</w>
         <c> </c>
         <w xml:id="bhw18-490900"
            n="a-0310"
            ecep:lem="pause"
            ecep:pos="vvn"
            ecep:reg="paused"
            ecep:spe="paus'd"
            ecep:syllab="1"
            ecep:pron="pɔːzd">paus'd</w>
         <c> </c>
         <w xml:id="bhw18-490910"
            n="a-0320"
            ecep:lem="to"
            ecep:pos="pc-acp"
            ecep:reg="to"
            ecep:spe="to"
            ecep:syllab="1"
            ecep:pron="tuː">to</w>
         <c> </c>
         <w xml:id="bhw18-490920"
            n="a-0330"
            ecep:lem="wish"
            ecep:pos="vvi"
            ecep:reg="wish"
            ecep:spe="wish"
            ecep:syllab="1"
            ecep:pron="wɪʃ">wish</w>
         <c> </c>
         <w xml:id="bhw18-490930"
            n="a-0340"
            ecep:lem="a"
            ecep:pos="dt"
            ecep:reg="a"
            ecep:spe="a"
            ecep:syllab="1"
            ecep:pron="ə">a</w>
         <c> </c>
         <w xml:id="bhw18-490940"
            n="a-0350"
            ecep:lem="witness"
            ecep:pos="n1"
            ecep:reg="witness"
            ecep:spe="witness"
            ecep:syllab="2"
            ecep:pron="ˈwɪtnəs">witness</w>
         <c> </c>
         <w xml:id="bhw18-490950"
            n="a-0360"
            ecep:lem="nigh"
            ecep:pos="av-j"
            ecep:reg="nigh"
            ecep:spe="nigh"
            ecep:syllab="1"
            ecep:pron="naɪ">nigh</w>
         <pc xml:id="bhw18-490960"
             n="a-0370"
             ecep:lem=","
             ecep:pos=","
             ecep:reg=","
             ecep:spe=",">,</pc>
      </l>
      <l xml:id="bhw18-l21290">
         <c> </c>
         <w xml:id="bhw18-490970"
            n="a-0380"
            ecep:lem="have"
            ecep:pos="vhb"
            ecep:reg="Have"
            ecep:spe="Have"
            ecep:syllab="1"
            ecep:pron="hæv">Have</w>
         <c> </c>
         <w xml:id="bhw18-490980"
            n="a-0390"
            ecep:lem="mingle"
            ecep:pos="vvn"
            ecep:reg="mingled"
            ecep:spe="mingled"
            ecep:syllab="2"
            ecep:pron="ˈmɪŋgld">mingled</w>
         <c> </c>
         <w xml:id="bhw18-490990"
            n="a-0400"
            ecep:lem="with"
            ecep:pos="p-acp"
            ecep:reg="with"
            ecep:spe="with"
            ecep:syllab="1"
            ecep:pron="wɪð">with</w>
         <c> </c>
         <w xml:id="bhw18-491000"
            n="a-0410"
            ecep:lem="your"
            ecep:pos="po22"
            ecep:reg="your"
            ecep:spe="your"
            ecep:syllab="1"
            ecep:pron="jɔː">your</w>
         <c> </c>
         <w xml:id="bhw18-491010"
            n="a-0420"
            ecep:lem="alm"
            ecep:pos="n2"
            ecep:reg="alms"
            ecep:spe="alms"
            ecep:syllab="1"
            ecep:pron="ɑːmz">alms</w>
         <pc xml:id="bhw18-491020"
             n="a-0430"
             ecep:lem=","
             ecep:pos=","
             ecep:reg=","
             ecep:spe=",">,</pc>
         <c> </c>
         <w xml:id="bhw18-491030"
            n="a-0440"
            ecep:lem="the"
            ecep:pos="dt"
            ecep:reg="the"
            ecep:spe="the"
            ecep:syllab="1"
            ecep:pron="ðiː">the</w>
         <c> </c>
         <w xml:id="bhw18-491040"
            n="a-0450"
            ecep:lem="unseen"
            ecep:pos="j"
            ecep:reg="unseen"
            ecep:spe="unseen"
            ecep:syllab="2"
            ecep:pron="ʌnˈsiːn">unseen</w>
         <c> </c>
         <w xml:id="bhw18-491050"
            n="a-0460"
            ecep:lem="tear"
            ecep:pos="n1"
            ecep:reg="tear"
            ecep:spe="tear"
            ecep:syllab="1"
            ecep:pron="tɪə">tear</w>
         <pc xml:id="bhw18-491060"
             n="a-0470"
             ecep:lem=","
             ecep:pos=","
             ecep:reg=","
             ecep:spe=",">,</pc>
      </l>
      <l xml:id="bhw18-l21295">
         <c> </c>
         <w xml:id="bhw18-491070"
            n="a-0480"
            ecep:lem="the"
            ecep:pos="dt"
            ecep:reg="The"
            ecep:spe="The"
            ecep:syllab="1"
            ecep:pron="ðiː">The</w>
         <c> </c>
         <w xml:id="bhw18-491080"
            n="a-0490"
            ecep:lem="secret"
            ecep:pos="j-jn"
            ecep:reg="secret"
            ecep:spe="secret"
            ecep:syllab="2"
            ecep:pron="ˈsiːkrət">secret</w>
         <c> </c>
         <w xml:id="bhw18-491090"
            n="a-0500"
            ecep:lem="sigh"
            ecep:pos="n1"
            ecep:reg="sigh"
            ecep:spe="sigh"
            ecep:syllab="1"
            ecep:pron="saɪ">sigh</w>
         <c> </c>
         <w xml:id="bhw18-491100"
            n="a-0510"
            ecep:lem="which"
            ecep:pos="r-crq"
            ecep:reg="which"
            ecep:spe="which"
            ecep:syllab="1"
            ecep:pron="wɪtʃ">which</w>
         <c> </c>
         <w xml:id="bhw18-491110"
            n="a-0520"
            ecep:lem="heaven"
            ecep:pos="n1"
            ecep:reg="heaven"
            ecep:spe="heav'n"
            ecep:syllab="1"
            ecep:pron="ˈhevn">heav'n</w>
         <c> </c>
         <w xml:id="bhw18-491120"
            n="a-0530"
            ecep:lem="alone"
            ecep:pos="av-j"
            ecep:reg="alone"
            ecep:spe="alone"
            ecep:syllab="2"
            ecep:pron="əˈləʊn">alone</w>
         <c> </c>
         <w xml:id="bhw18-491130"
            n="a-0540"
            ecep:lem="can"
            ecep:pos="vmd"
            ecep:reg="could"
            ecep:spe="could"
            ecep:syllab="1"
            ecep:pron="kʊd">could</w>
         <c> </c>
         <w xml:id="bhw18-491140"
            n="a-0550"
            ecep:lem="hear"
            ecep:pos="vvi"
            ecep:reg="hear"
            ecep:spe="hear"
            ecep:syllab="1"
            ecep:pron="hɪə">hear</w>
         <pc xml:id="bhw18-491150"
             n="a-0560"
             ecep:lem=";"
             ecep:pos=";"
             ecep:reg=";"
             ecep:spe=";">;</pc>
      </l>
      <l xml:id="bhw18-l21300">
         <c> </c>
         <w xml:id="bhw18-491160"
            n="a-0570"
            ecep:lem="be"
            ecep:pos="vbb"
            ecep:reg="Be"
            ecep:spe="Be"
            ecep:syllab="1"
            ecep:pron="biː">Be</w>
         <c> </c>
         <w xml:id="bhw18-491170"
            n="a-0580"
            ecep:lem="you"
            ecep:pos="png22"
            ecep:reg="yours"
            ecep:spe="yours"
            ecep:syllab="1"
            ecep:pron="jɔːz">yours</w>
         <pc xml:id="bhw18-491180"
             n="a-0590"
             ecep:lem=","
             ecep:pos=","
             ecep:reg=","
             ecep:spe=",">,</pc>
         <c> </c>
         <w xml:id="bhw18-491190"
            n="a-0600"
            ecep:lem="when"
            ecep:pos="c-crq"
            ecep:reg="when"
            ecep:spe="when"
            ecep:syllab="1"
            ecep:pron="wen">when</w>
         <c> </c>
         <w xml:id="bhw18-491200"
            n="a-0610"
            ecep:lem="life"
            ecep:pos="n1"
            ecep:reg="life"
            ecep:spe="life"
            ecep:syllab="1"
            ecep:pron="laɪf">life</w>
         <c> </c>
         <w xml:id="bhw18-491210"
            n="a-0620"
            ecep:lem="shall"
            ecep:pos="vmb"
            ecep:reg="shall"
            ecep:spe="shall"
            ecep:syllab="1"
            ecep:pron="ʃæl">shall</w>
         <c> </c>
         <w xml:id="bhw18-491220"
            n="a-0630"
            ecep:lem="reach"
            ecep:pos="vvi"
            ecep:reg="reach"
            ecep:spe="reach"
            ecep:syllab="1"
            ecep:pron="riːtʃ">reach</w>
         <c> </c>
         <w xml:id="bhw18-491230"
            n="a-0640"
            ecep:lem="the"
            ecep:pos="dt"
            ecep:reg="the"
            ecep:spe="the"
            ecep:syllab="1"
            ecep:pron="ðiː">the</w>
         <c> </c>
         <w xml:id="bhw18-491240"
            n="a-0650"
            ecep:lem="close"
            ecep:pos="j-vvg"
            ecep:reg="closing"
            ecep:spe="closing"
            ecep:syllab="2"
            ecep:pron="kləʊzɪŋ">closing</w>
         <c> </c>
         <w xml:id="bhw18-491250"
            n="a-0660"
            ecep:lem="scene"
            ecep:pos="n1"
            ecep:reg="scene"
            ecep:spe="scene"
            ecep:syllab="1"
            ecep:pron="siːn">scene</w>
         <pc xml:id="bhw18-491260"
             n="a-0670"
             ecep:lem=","
             ecep:pos=","
             ecep:reg=","
             ecep:spe=",">,</pc>
      </l>
      <l xml:id="bhw18-l21305">
         <c> </c>
         <w xml:id="bhw18-491270"
            n="a-0680"
            ecep:lem="to"
            ecep:pos="pc-acp"
            ecep:reg="To"
            ecep:spe="To"
            ecep:syllab="1"
            ecep:pron="tuː">To</w>
         <c> </c>
         <w xml:id="bhw18-491280"
            n="a-0690"
            ecep:lem="read"
            ecep:pos="vvi"
            ecep:reg="read"
            ecep:spe="read"
            ecep:syllab="1"
            ecep:pron="riːd">read</w>
         <c> </c>
         <w xml:id="bhw18-491290"
            n="a-0700"
            ecep:lem="its"
            ecep:pos="po31"
            ecep:reg="its"
            ecep:spe="its"
            ecep:syllab="1"
            ecep:pron="ɪts">its</w>
         <c> </c>
         <w xml:id="bhw18-491300"
            n="a-0710"
            ecep:lem="record"
            ecep:pos="n1"
            ecep:reg="record"
            ecep:spe="record"
            ecep:syllab="2"
            ecep:pron="ˈrekɔːd">record</w>
         <c> </c>
         <w xml:id="bhw18-491310"
            n="a-0720"
            ecep:lem="with"
            ecep:pos="p-acp"
            ecep:reg="with"
            ecep:spe="with"
            ecep:syllab="1"
            ecep:pron="wɪð">with</w>
         <c> </c>
         <w xml:id="bhw18-491320"
            n="a-0730"
            ecep:lem="a"
            ecep:pos="dt"
            ecep:reg="a"
            ecep:spe="a"
            ecep:syllab="1"
            ecep:pron="ə">a</w>
         <c> </c>
         <w xml:id="bhw18-491330"
            n="a-0740"
            ecep:lem="hope"
            ecep:pos="n1"
            ecep:reg="hope"
            ecep:spe="hope"
            ecep:syllab="1"
            ecep:pron="həʊp">hope</w>
         <c> </c>
         <w xml:id="bhw18-491340"
            n="a-0750"
            ecep:lem="serene"
            ecep:pos="j"
            ecep:reg="serene"
            ecep:spe="serene"
            ecep:syllab="2"
            ecep:pron="sɪˈriːn">serene</w>
         <pc xml:id="bhw18-491350"
             n="a-0760"
             ecep:lem=";"
             ecep:pos=";"
             ecep:reg=";"
             ecep:spe=";">;</pc>
      </l>
      <l xml:id="bhw18-l21310">
         <c> </c>
         <w xml:id="bhw18-491360"
            n="a-0770"
            ecep:lem="and"
            ecep:pos="cc"
            ecep:reg="And"
            ecep:spe="And"
            ecep:syllab="1"
            ecep:pron="ænd">And</w>
         <c> </c>
         <w xml:id="bhw18-491370"
            n="a-0780"
            ecep:lem="you"
            ecep:pos="png22"
            ecep:reg="yours"
            ecep:spe="yours"
            ecep:syllab="1"
            ecep:pron="jɔːz">yours</w>
         <c> </c>
         <w xml:id="bhw18-491380"
            n="a-0790"
            ecep:lem="to"
            ecep:pos="pc-acp"
            ecep:reg="to"
            ecep:spe="to"
            ecep:syllab="1"
            ecep:pron="tuː">to</w>
         <c> </c>
         <w xml:id="bhw18-491390"
            n="a-0800"
            ecep:lem="listen"
            ecep:pos="vvi"
            ecep:reg="listen"
            ecep:spe="listen"
            ecep:syllab="2"
            ecep:pron="ˈlɪsn">listen</w>
         <pc xml:id="bhw18-491400"
             n="a-0810"
             ecep:lem=","
             ecep:pos=","
             ecep:reg=","
             ecep:spe=",">,</pc>
         <c> </c>
         <w xml:id="bhw18-491410"
            n="a-0820"
            ecep:lem="while"
            ecep:pos="cs"
            ecep:reg="while"
            ecep:spe="while"
            ecep:syllab="1"
            ecep:pron="ˈwaɪl">while</w>
         <c> </c>
         <w xml:id="bhw18-491420"
            n="a-0830"
            ecep:lem="a"
            ecep:pos="dt"
            ecep:reg="a"
            ecep:spe="a"
            ecep:syllab="1"
            ecep:pron="ə">a</w>
         <c> </c>
         <w xml:id="bhw18-491430"
            n="a-0840"
            ecep:lem="voice"
            ecep:pos="n1"
            ecep:reg="voice"
            ecep:spe="voice"
            ecep:syllab="1"
            ecep:pron="vɔɪs">voice</w>
         <c> </c>
         <w xml:id="bhw18-491440"
            n="a-0850"
            ecep:lem="of"
            ecep:pos="pp-f"
            ecep:reg="of"
            ecep:spe="of"
            ecep:syllab="1"
            ecep:pron="ɒv">of</w>
         <c> </c>
         <w xml:id="bhw18-491450"
            n="a-0860"
            ecep:lem="love"
            ecep:pos="n1"
            ecep:reg="love"
            ecep:spe="love"
            ecep:syllab="1"
            ecep:pron="lʌv">love</w>
      </l>
      <l xml:id="bhw18-l21315">
         <c> </c>
         <w xml:id="bhw18-491460"
            n="a-0870"
            ecep:lem="proclaim"
            ecep:pos="vvz"
            ecep:reg="Proclaims"
            ecep:spe="Proclaims"
            ecep:syllab="2"
            ecep:pron="prəˈkleɪmz">Proclaims</w>
         <c> </c>
         <w xml:id="bhw18-491470"
            n="a-0880"
            ecep:lem="your"
            ecep:pos="po22"
            ecep:reg="your"
            ecep:spe="your"
            ecep:syllab="1"
            ecep:pron="jɔː">your</w>
         <c> </c>
         <w xml:id="bhw18-491480"
            n="a-0890"
            ecep:lem="bright"
            ecep:pos="j"
            ecep:reg="bright"
            ecep:spe="bright"
            ecep:syllab="1"
            ecep:pron="braɪt">bright</w>
         <c> </c>
         <w xml:id="bhw18-491490"
            n="a-0900"
            ecep:lem="inheritance"
            ecep:pos="n1"
            ecep:reg="inheritance"
            ecep:spe="inheritance"
            ecep:syllab="4"
            ecep:pron="ɪnˈherɪtns">inheritance</w>
         <c> </c>
         <w xml:id="bhw18-491500"
            n="a-0910"
            ecep:lem="above"
            ecep:pos="a-acp"
            ecep:reg="above"
            ecep:spe="above"
            ecep:syllab="2"
            ecep:pron="əˈbʌv">above</w>
         <pc xml:id="bhw18-491510"
             n="a-0920"
             unit="sentence"
             ecep:lem="."
             ecep:pos="."
             ecep:reg="."
             ecep:spe=".">.</pc>
         <c> </c>
      </l>
   </lg>
</div>
